Workbook

Sheet Main
A1: Year | B1: Annual Budget | C1: Outside Income | D1: Portfolio Withdrawal to Cover Annual Budget | E1: Total Tax Liability | F1: Taxes as percent of Budgeted Income | G1: Taxable Pool End | H1: Inherited IRA End | I1: Roth IRAs End | J1: Total Net Assets
A2: 2026 | B2: 0 | C2: ='Outside Income'!F2 -> 60338 | D2: =MAX(0, B2-C2) -> 0 | E2: =Taxes!Z2 -> 39820.093 | G2: ='Capital Gains'!I2 -> 3964954.7 | H2: ='Inherited and Roth IRA'!H2 -> 590049.83 | I2: ='Inherited and Roth IRA'!O2 -> 2133346.2 | J2: =SUM(G2:I2) -> 6688350.8
A3: 2027 | B3: 600000 | C3: ='Outside Income'!F3 -> 170117.13 | D3: =MAX(0, B3-C3) -> 429882.87 | E3: =Taxes!Z3 -> 16420.303 | F3: =E3/B3 -> 0.027367172 | G3: ='Capital Gains'!I3 -> 3923929.7 | H3: ='Inherited and Roth IRA'!H3 -> 611965.97 | I3: ='Inherited and Roth IRA'!O3 -> 2346680.8 | J3: =SUM(G3:I3) -> 6882576.6
A4: =A3+1 -> 2028 | B4: =B3*(1+Assumptions!B$11) -> 618000 | C4: ='Outside Income'!F4 -> 173992.85 | D4: =MAX(0, B4-C4) -> 444007.15 | E4: =Taxes!Z4 -> 19162.953 | F4: =E4/B4 -> 0.031008014 | G4: ='Capital Gains'!I4 -> 3862714.1 | H4: ='Inherited and Roth IRA'!H4 -> 632364.83 | I4: ='Inherited and Roth IRA'!O4 -> 2581348.9 | J4: =SUM(G4:I4) -> 7076427.8
A5: =A4+1 -> 2029 | B5: =B4*(1+Assumptions!B$11) -> 636540 | C5: ='Outside Income'!F5 -> 178210.77 | D5: =MAX(0, B5-C5) -> 458329.23 | E5: =Taxes!Z5 -> 22554.339 | F5: =E5/B5 -> 0.035432714 | G5: ='Capital Gains'!I5 -> 3778867.2 | H5: ='Inherited and Roth IRA'!H5 -> 650723.81 | I5: ='Inherited and Roth IRA'!O5 -> 2839483.8 | J5: =SUM(G5:I5) -> 7269074.8
A6: =A5+1 -> 2030 | B6: =B5*(1+Assumptions!B$11) -> 655636.2 | C6: ='Outside Income'!F6 -> 182804.67 | D6: =MAX(0, B6-C6) -> 472831.53 | E6: =Taxes!Z6 -> 26833.551 | F6: =E6/B6 -> 0.040927501 | G6: ='Capital Gains'!I6 -> 3669699.6 | H6: ='Inherited and Roth IRA'!H6 -> 666430.94 | I6: ='Inherited and Roth IRA'!O6 -> 3123432.2 | J6: =SUM(G6:I6) -> 7459562.7
A7: =A6+1 -> 2031 | B7: =B6*(1+Assumptions!B$11) -> 675305.29 | C7: ='Outside Income'!F7 -> 187811.7 | D7: =MAX(0, B7-C7) -> 487493.59 | E7: =Taxes!Z7 -> 30906.741 | F7: =E7/B7 -> 0.045767064 | G7: ='Capital Gains'!I7 -> 3532248.6 | H7: ='Inherited and Roth IRA'!H7 -> 678772.25 | I7: ='Inherited and Roth IRA'!O7 -> 3435775.4 | J7: =SUM(G7:I7) -> 7646796.3
A8: =A7+1 -> 2032 | B8: =B7*(1+Assumptions!B$11) -> 695564.44 | C8: ='Outside Income'!F8 -> 193272.69 | D8: =MAX(0, B8-C8) -> 502291.76 | E8: =Taxes!Z8 -> 30922.417 | F8: =E8/B8 -> 0.044456581 | G8: ='Capital Gains'!I8 -> 3363252.1 | H8: ='Inherited and Roth IRA'!H8 -> 686917.52 | I8: ='Inherited and Roth IRA'!O8 -> 3779353 | J8: =SUM(G8:I8) -> 7829522.6
A9: =A8+1 -> 2033 | B9: =B8*(1+Assumptions!B$11) -> 716431.38 | C9: ='Outside Income'!F9 -> 199232.57 | D9: =MAX(0, B9-C9) -> 517198.8 | E9: =Taxes!Z9 -> 25902.929 | F9: =E9/B9 -> 0.036155491 | G9: ='Capital Gains'!I9 -> 3159119.2 | H9: ='Inherited and Roth IRA'!H9 -> 689904.12 | I9: ='Inherited and Roth IRA'!O9 -> 4157288.3 | J9: =SUM(G9:I9) -> 8006311.6
A10: =A9+1 -> 2034 | B10: =B9*(1+Assumptions!B$11) -> 737924.32 | C10: ='Outside Income'!F10 -> 205740.78 | D10: =MAX(0, B10-C10) -> 532183.54 | E10: =Taxes!Z10 -> 30016.875 | F10: =E10/B10 -> 0.040677444 | G10: ='Capital Gains'!I10 -> 2915898.6 | H10: ='Inherited and Roth IRA'!H10 -> 686618.86 | I10: ='Inherited and Roth IRA'!O10 -> 4573017.1 | J10: =SUM(G10:I10) -> 8175534.5
A11: =A10+1 -> 2035 | B11: =B10*(1+Assumptions!B$11) -> 760062.05 | C11: ='Outside Income'!F11 -> 212851.65 | D11: =MAX(0, B11-C11) -> 547210.4 | E11: =Taxes!Z11 -> 34052.5 | F11: =E11/B11 -> 0.044802263 | G11: ='Capital Gains'!I11 -> 2629243.9 | H11: ='Inherited and Roth IRA'!H11 -> 675777.51 | I11: ='Inherited and Roth IRA'!O11 -> 5030318.8 | J11: =SUM(G11:I11) -> 8335340.2
A12: =A11+1 -> 2036 | B12: =B11*(1+Assumptions!B$11) -> 782863.91 | C12: ='Outside Income'!F12 -> 220624.97 | D12: =MAX(0, B12-C12) -> 562238.94 | E12: =Taxes!Z12 -> 38017.027 | F12: =E12/B12 -> 0.048561477 | G12: ='Capital Gains'!I12 -> 2294375.5 | H12: ='Inherited and Roth IRA'!H12 -> 655901.7 | I12: ='Inherited and Roth IRA'!O12 -> 5533350.7 | J12: =SUM(G12:I12) -> 8483627.9
A13: =A12+1 -> 2037 | B13: =B12*(1+Assumptions!B$11) -> 806349.83 | C13: ='Outside Income'!F13 -> 229126.52 | D13: =MAX(0, B13-C13) -> 577223.31 | E13: =Taxes!Z13 -> 41917.177 | F13: =E13/B13 -> 0.05198386 | G13: ='Capital Gains'!I13 -> 1906038.9 | H13: ='Inherited and Roth IRA'!H13 -> 625292.95 | I13: ='Inherited and Roth IRA'!O13 -> 6086685.8 | J13: =SUM(G13:I13) -> 8618017.6
A14: =A13+1 -> 2038 | B14: =B13*(1+Assumptions!B$11) -> 830540.32 | C14: ='Outside Income'!F14 -> 238428.6 | D14: =MAX(0, B14-C14) -> 592111.72 | E14: =Taxes!Z14 -> 45759.162 | F14: =E14/B14 -> 0.055095653 | G14: ='Capital Gains'!I14 -> 1458459.2 | H14: ='Inherited and Roth IRA'!H14 -> 582003.44 | I14: ='Inherited and Roth IRA'!O14 -> 6695354.3 | J14: =SUM(G14:I14) -> 8735816.9
A15: =A14+1 -> 2039 | B15: =B14*(1+Assumptions!B$11) -> 855456.53 | C15: ='Outside Income'!F15 -> 248610.79 | D15: =MAX(0, B15-C15) -> 606845.74 | E15: =Taxes!Z15 -> 49661.988 | F15: =E15/B15 -> 0.058053199 | G15: ='Capital Gains'!I15 -> 945290.91 | H15: ='Inherited and Roth IRA'!H15 -> 523803.1 | I15: ='Inherited and Roth IRA'!O15 -> 7364889.8 | J15: =SUM(G15:I15) -> 8833983.8
... A31: =A30+1 -> 2055 | B31: =B30*(1+Assumptions!B$11) -> 1372756.6 | C31: ='Outside Income'!F31 -> 152593.06 | D31: =MAX(0, B31-C31) -> 1220163.5 | E31: =Taxes!Z31 -> 0 | F31: =E31/B31 -> 0 | G31: ='Capital Gains'!I31 -> 0 | H31: ='Inherited and Roth IRA'!H31 -> 0 | I31: ='Inherited and Roth IRA'!O31 -> 7623643.7 | J31: =SUM(G31:I31) -> 7623643.7
B33: =SUM(B2:B31) -> 27131310 | C33: =SUM(C2:C31) -> 5692499.8 | D33: =SUM(D2:D31) -> 21499148 | E33: =SUM(E2:E31) -> 575757.71

Sheet Cash Flow
A1: Year | B1: Ilene's Age | C1: Annual Budget | D1: Outside Income | E1: Portfolio Withdrawal to Cover Annual Budget | F1: Taxable Pool Funding | G1: Roth IRA Funding | H1: Inherited IRA Funding | I1: Total Net Assets | J1: Total Taxes Due
A2: 2026 | B2: 65 | C2: =Main!B2 -> 0 | D2: =Main!C2 -> 60338 | E2: =Main!D2 -> 0 | F2: ='Capital Gains'!D2 -> 0 | G2: =MAX(0, E2 - F2) -> 0 | H2: ='Inherited and Roth IRA'!G2 -> 33717.133 | I2: =Main!J2 -> 6688350.8 | J2: =Main!E2 -> 39820.093
A3: =A2+1 -> 2027 | B3: =B2+1 -> 66 | C3: =Main!B3 -> 600000 | D3: =Main!C3 -> 170117.13 | E3: =Main!D3 -> 429882.87 | F3: ='Capital Gains'!D3 -> 429882.87 | G3: =MAX(0, E3 - F3) -> 0 | H3: ='Inherited and Roth IRA'!G3 -> 33717.133 | I3: =Main!J3 -> 6882576.6 | J3: =Main!E3 -> 16420.303
A4: =A3+1 -> 2028 | B4: =B3+1 -> 67 | C4: =Main!B4 -> 618000 | D4: =Main!C4 -> 173992.85 | E4: =Main!D4 -> 444007.15 | F4: ='Capital Gains'!D4 -> 444007.15 | G4: =MAX(0, E4 - F4) -> 0 | H4: ='Inherited and Roth IRA'!G4 -> 37088.846 | I4: =Main!J4 -> 7076427.8 | J4: =Main!E4 -> 19162.953
A5: =A4+1 -> 2029 | B5: =B4+1 -> 68 | C5: =Main!B5 -> 636540 | D5: =Main!C5 -> 178210.77 | E5: =Main!D5 -> 458329.23 | F5: ='Capital Gains'!D5 -> 458329.23 | G5: =MAX(0, E5 - F5) -> 0 | H5: ='Inherited and Roth IRA'!G5 -> 40797.731 | I5: =Main!J5 -> 7269074.8 | J5: =Main!E5 -> 22554.339
A6: =A5+1 -> 2030 | B6: =B5+1 -> 69 | C6: =Main!B6 -> 655636.2 | D6: =Main!C6 -> 182804.67 | E6: =Main!D6 -> 472831.53 | F6: ='Capital Gains'!D6 -> 472831.53 | G6: =MAX(0, E6 - F6) -> 0 | H6: ='Inherited and Roth IRA'!G6 -> 44877.504 | I6: =Main!J6 -> 7459562.7 | J6: =Main!E6 -> 26833.551
A7: =A6+1 -> 2031 | B7: =B6+1 -> 70 | C7: =Main!B7 -> 675305.29 | D7: =Main!C7 -> 187811.7 | E7: =Main!D7 -> 487493.59 | F7: ='Capital Gains'!D7 -> 487493.59 | G7: =MAX(0, E7 - F7) -> 0 | H7: ='Inherited and Roth IRA'!G7 -> 49365.255 | I7: =Main!J7 -> 7646796.3 | J7: =Main!E7 -> 30906.741
A8: =A7+1 -> 2032 | B8: =B7+1 -> 71 | C8: =Main!B8 -> 695564.44 | D8: =Main!C8 -> 193272.69 | E8: =Main!D8 -> 502291.76 | F8: ='Capital Gains'!D8 -> 502291.76 | G8: =MAX(0, E8 - F8) -> 0 | H8: ='Inherited and Roth IRA'!G8 -> 54301.78 | I8: =Main!J8 -> 7829522.6 | J8: =Main!E8 -> 30922.417
A9: =A8+1 -> 2033 | B9: =B8+1 -> 72 | C9: =Main!B9 -> 716431.38 | D9: =Main!C9 -> 199232.57 | E9: =Main!D9 -> 517198.8 | F9: ='Capital Gains'!D9 -> 517198.8 | G9: =MAX(0, E9 - F9) -> 0 | H9: ='Inherited and Roth IRA'!G9 -> 59731.958 | I9: =Main!J9 -> 8006311.6 | J9: =Main!E9 -> 25902.929
A10: =A9+1 -> 2034 | B10: =B9+1 -> 73 | C10: =Main!B10 -> 737924.32 | D10: =Main!C10 -> 205740.78 | E10: =Main!D10 -> 532183.54 | F10: ='Capital Gains'!D10 -> 532183.54 | G10: =MAX(0, E10 - F10) -> 0 | H10: ='Inherited and Roth IRA'!G10 -> 65705.154 | I10: =Main!J10 -> 8175534.5 | J10: =Main!E10 -> 30016.875
A11: =A10+1 -> 2035 | B11: =B10+1 -> 74 | C11: =Main!B11 -> 760062.05 | D11: =Main!C11 -> 212851.65 | E11: =Main!D11 -> 547210.4 | F11: ='Capital Gains'!D11 -> 547210.4 | G11: =MAX(0, E11 - F11) -> 0 | H11: ='Inherited and Roth IRA'!G11 -> 72275.669 | I11: =Main!J11 -> 8335340.2 | J11: =Main!E11 -> 34052.5
A12: =A11+1 -> 2036 | B12: =B11+1 -> 75 | C12: =Main!B12 -> 782863.91 | D12: =Main!C12 -> 220624.97 | E12: =Main!D12 -> 562238.94 | F12: ='Capital Gains'!D12 -> 562238.94 | G12: =MAX(0, E12 - F12) -> 0 | H12: ='Inherited and Roth IRA'!G12 -> 79503.236 | I12: =Main!J12 -> 8483627.9 | J12: =Main!E12 -> 38017.027
A13: =A12+1 -> 2037 | B13: =B12+1 -> 76 | C13: =Main!B13 -> 806349.83 | D13: =Main!C13 -> 229126.52 | E13: =Main!D13 -> 577223.31 | F13: ='Capital Gains'!D13 -> 577223.31 | G13: =MAX(0, E13 - F13) -> 0 | H13: ='Inherited and Roth IRA'!G13 -> 87453.56 | I13: =Main!J13 -> 8618017.6 | J13: =Main!E13 -> 41917.177
A14: =A13+1 -> 2038 | B14: =B13+1 -> 77 | C14: =Main!B14 -> 830540.32 | D14: =Main!C14 -> 238428.6 | E14: =Main!D14 -> 592111.72 | F14: ='Capital Gains'!D14 -> 592111.72 | G14: =MAX(0, E14 - F14) -> 0 | H14: ='Inherited and Roth IRA'!G14 -> 96198.916 | I14: =Main!J14 -> 8735816.9 | J14: =Main!E14 -> 45759.162
... A31: =A30+1 -> 2055 | B31: =B30+1 -> 94 | C31: =Main!B31 -> 1372756.6 | D31: =Main!C31 -> 152593.06 | E31: =Main!D31 -> 1220163.5 | F31: ='Capital Gains'!D31 -> 0 | G31: =MAX(0, E31 - F31) -> 1220163.5 | H31: ='Inherited and Roth IRA'!G31 -> 0 | I31: =Main!J31 -> 7623643.7 | J31: =Main!E31 -> 0
C33: =SUM(C2:C31) -> 27131310 | D33: =SUM(D2:D31) -> 5692499.8 | E33: =SUM(E2:E31) -> 21499148 | F33: =SUM(F2:F31) -> 7710771.9 | G33: =SUM(G2:G31) -> 13788376 | H33: =SUM(H2:H31) -> 1485979.4 | J33: =SUM(J2:J31) -> 575757.71

Sheet Assumptions
D1: Price per share | E1: Number of Shares | F1: Appreciation in Remainder of 2026 | G1: 2026 Year-end balance
A2: Initial Taxable Pool | B2: 3803339 | C2: Opening balance | D2: 89.3096 | E2: =B2/D2 -> 42586.004 | F2: =(B2*B5)*C7 -> 161615.7 | G2: =B2+F2 -> 3964954.7
A3: Initial Inherited IRA Pool | B3: 600567 | C3: Opening balance | D3: 45.53 | E3: =B3/D3 -> 13190.578 | F3: =(B3*B$8)*C7 -> 23199.963 | G3: =B3+F3 -> 623766.96
A4: Initial Roth IRA Pool | B4: 2054000 | C4: Opening balance | D4: 45.53 | E4: =B4/D4 -> 45113.112 | F4: =(B4*B$8)*C7 -> 79346.225 | G4: =B4+F4 -> 2133346.2
A5: Vanguard VUG annual return | B5: 0.11 | C5: =B5*0.0416666 -> 0.004583326
A6: VUG annual dividend | B6: 0.0043
A7: Maximum cap on Viatar business losses | B7: 400000 | C7: 0.386301 | D7: Prorate appreciation from 8-15 to 12-31-2026
A8: Vanguard VLXVX annual return | B8: 0.1
A9: Margin Debt Interest Rate | B9: 0.065
A10: Out-of-Pocket Tax Ceiling | B10: 35000
A11: Budget Inflation Rate | B11: 0.03
A12: Combined Ordinary Tax Rate | B12: 0.2837
A13: NJ Personal & Senior Exemptions (MFJ Age 65+) | B13: 4000
A14: NJ tax rate | B14: 0.0675
A15: Max Extra IRA Paydown Cap | B15: 150000
A16: VUG opening balance stock price | B16: 83.48
A17: VLXVX opening balance stock price | B17: 43.74
A18: NJ BRACKETS (MFJ) | B18: Bracket Start | C18: Marginal Rate | D18: Base Tax Amount | E18: Description
A20: NJ Bracket 1 | B20: 0 | C20: 0.014 | D20: 0 | E20: $0 to $20,000
A21: NJ Bracket 2 | B21: 20000 | C21: 0.0175 | D21: 280 | E21: $20,001 to $50,000
A22: NJ Bracket 3 | B22: 50000 | C22: 0.0245 | D22: 805 | E22: $50,001 to $70,000
A23: NJ Bracket 4 | B23: 70000 | C23: 0.035 | D23: 1295.5 | E23: $70,001 to $80,000
A24: NJ Bracket 5 | B24: 80000 | C24: 0.0553 | D24: 1645 | E24: $80,001 to $150,000
A25: NJ Bracket 6 | B25: 150000 | C25: 0.0637 | D25: 5512.5 | E25: $150,001 to $500,000
A26: NJ Bracket 7 | B26: 500000 | C26: 0.0897 | D26: 27807.5 | E26: $500,001 to $1,000,000
A27: NJ Bracket 8 | B27: 1000000 | C27: 0.1075 | D27: 72657.5 | E27: Over $1,000,000
A28: Accelerated IRA Target Draw | B28: 0
A29: FEDERAL ORDINARY INCOME TAX BRACKETS (2026 MFJ) | B29: Bracket Start | C29: Marginal Rate | D29: Base Tax Amount | E29: Taxable Income Range Description
A30: Fed Ord Bracket 1 | B30: 0 | C30: 0.1 | D30: 0 | E30: 10% Rate ($0 to $23,200)
A31: Fed Ord Bracket 2 | B31: 23200 | C31: 0.12 | D31: 2320 | E31: 12% Rate ($23,201 to $94,300)
A32: Fed Ord Bracket 3 | B32: 94300 | C32: 0.22 | D32: 10852 | E32: 22% Rate ($94,301 to $201,050)
A33: Fed Ord Bracket 4 | B33: 201050 | C33: 0.24 | D33: 34337 | E33: 24% Rate ($201,051 to $383,900)
A34: Fed Ord Bracket 5 | B34: 383900 | C34: 0.32 | D34: 78221 | E34: 32% Rate ($383,901 to $487,450)
A35: Fed Ord Bracket 6 | B35: 487450 | C35: 0.35 | D35: 111357 | E35: 35% Rate ($487,451 to $731,200)
A36: Fed Ord Bracket 7 | B36: 731200 | C36: 0.37 | D36: 196669.5 | E36: 37% Rate (Over $731,200)
A37: IRC § 163(d) Capital Gains Election Amount
A39: FEDERAL CAPITAL GAINS TAX BRACKETS (2026 MFJ) | B39: Bracket Start | C39: Marginal Rate | D39: Base Tax Amount | E39: Taxable Income Range Description
A40: Fed CG Bracket 1 | B40: 0 | C40: 0 | D40: 0 | E40: 0% Rate ($0 to $94,050)
A41: Fed CG Bracket 2 | B41: 94050 | C41: 0.15 | D41: 0 | E41: 15% Rate ($94,051 to $583,750)
A42: Fed CG Bracket 3 | B42: 583750 | C42: 0.2 | D42: 73455 | E42: 20% Rate (Over $583,750)
A44: OBBBA SALT & DEDUCTION PARAMETERS | B44: Value | C44: Notes / Description
A45: SALT Base Cap (OBBBA 2026) | B45: 40400 | C45: 2026 Married Filing Jointly base SALT cap
A46: SALT MAGI Phase-Down Threshold | B46: 505000 | C46: MAGI threshold where phase-down begins
A47: SALT Phase-Down Rate | B47: 0.3 | C47: 30 cents per dollar cap reduction above threshold
A48: SALT Statutory Floor Cap | B48: 10000 | C48: Statutory minimum SALT cap floor
A49: Medical Deduction AGI Floor Rate | B49: 0.075 | C49: 7.5% of AGI floor for Schedule A
A50: LTCG § 163(d) Election Cap | B50: 38918
A51: Target Taxable Ordinary Income | B51: 20000
A53: Roth conversion | C53: election cap
A54: 2026 | B54: ='Inherited and Roth IRA'!K2 -> 200000 | C54: =if(B54>0,0,999999) -> 0
A55: 2027 | B55: ='Inherited and Roth IRA'!K3 -> 200000 | C55: =if(B55>0,0,999999) -> 0
A56: 2028 | B56: ='Inherited and Roth IRA'!K4 -> 200000 | C56: =if(B56>0,0,999999) -> 0
A57: 2029 | B57: ='Inherited and Roth IRA'!K5 -> 200000 | C57: =if(B57>0,0,999999) -> 0
A58: 2030 | B58: ='Inherited and Roth IRA'!K6 -> 200000 | C58: =if(B58>0,0,999999) -> 0
A59: 2031 | B59: ='Inherited and Roth IRA'!K7 -> 200000 | C59: =if(B59>0,0,999999) -> 0
A60: 2032 | B60: ='Inherited and Roth IRA'!K8 -> 144757.17 | C60: =if(B60>0,0,999999) -> 0
A61: 2033 | B61: ='Inherited and Roth IRA'!K9 -> 0 | C61: =if(B61>0,0,999999) -> 999999
A62: 2034 | B62: ='Inherited and Roth IRA'!K10 -> 0 | C62: =if(B62>0,0,999999) -> 999999
A63: 2035 | B63: ='Inherited and Roth IRA'!K11 -> 0 | C63: =if(B63>0,0,999999) -> 999999

Sheet Taxes
A1: Year | B1: Social Security Taxable Portion | C1: Inherited IRA Distributions | D1: Dividend Income | E1: Roth Conversion Income | F1: Optimal § 163(d) Election | G1: Federal Gross Ordinary Income | H1: Viatar Business Loss | I1: Federal Net Ordinary Income | J1: Unabsorbed Viatar Loss | K1: Realized Capital Gains | L1: Capital Gains After Viatar Loss | M1: Adjusted Gross Income (AGI) | N1: Schedule A Itemized Deductions | O1: Taxable Ordinary Income | P1: Federal Tax on Ordinary Income | Q1: Realized Capital Gains (Baseline) | R1: Investment Interest Carryforward Applied to LTCG | S1: Unused Schedule A Deduction | T1: Capital Gains Subject to LTCG Tax | U1: Federal Capital Gains Tax | V1: 3.8% Medicare Surtax / NIIT (IRC § 1411) | W1: Gross Federal Tax Liability | X1: NJ Taxable Income | Y1: NJ Tax Liability | Z1: Total Federal and NJ Taxes | AA1: Viatar Total Loss Applied
A2: 2026 | B2: ='Outside Income'!D2 * 0.85 -> 27268 | C2: ='Outside Income'!E2 -> 28258 | D2: =IF('Capital Gains'!G2<=0, 0, 'Outside Income'!G2) -> 48872 | E2: ='Inherited and Roth IRA'!K2 -> 200000 | F2: =IF('Capital Gains'!F2<=0, 0, MIN(MAX(0, 'Schedule A'!P2 - D2), 'Capital Gains'!F2)) -> 38918 | G2: =B2 + C2 + D2 + E2 + F2 -> 343316 | H2: =MAX(0, MIN(400000, G2 - ((20000 + 'Schedule A'!J2 + 'Schedule A'!K2 + 'Schedule A'!L2 + 'Schedule A'!Q2 + 'Schedule A'!C2 - 0.075 * MAX(0, K2 - F2)) / 1.075))) -> 161821.12 | I2: =MAX(0, G2 - H2) -> 181494.88 | J2: =MAX(0, 400000 - G2) -> 56684 | K2: =IF('Capital Gains'!G2<=0, 0, MAX(0, 'Capital Gains'!F2 - F2)) -> 274598 | L2: =IF('Capital Gains'!G2<=0, 0, MAX(0, K2 - J2)) -> 217914 | M2: =I2 + L2 -> 399408.88 | N2: ='Schedule A'!M2 -> 162827.33 | O2: =MAX(0, I2 - N2) -> 18667.55 | P2: =IF(O2<=0, 0, IF(O2<=Assumptions!$B$30, O2*Assumptions!$C$29, IF(O2<=Assumptions!$B$31, Assumptions!$D$30 + (O2-Assumptions!$B$30)*Assumptions!$C$30, IF(O2<=Assumptions!$B$32, Assumptions!$D$31 + (O2-Assumptions!$B$31)*Assumptions!$C$31, IF(O2<=Assumptions!$B$33, Assumptions!$D$32 + (O2-Assumptions!$B$32)*Assumptions!$C$32, IF(O2<=Assumptions!$B$34, Assumptions!$D$33 + (O2-Assumptions!$B$33)*Assumptions!$C$33, IF(O2<=Assumptions!$B$35, Assumptions!$D$34 + (O2-Assumptions!$B$34)*Assumptions!$C$34, Assumptions!$D$35 + (O2-Assumptions!$B$35)*Assumptions!$C$35))))))) -> 1866.755 | Q2: =L2 -> 217914 | R2: =IF('Capital Gains'!G2<=0, 0, MIN('Schedule A'!R2, L2)) -> 0 | S2: =MAX(0, N2 - I2) -> 0 | T2: =IF('Capital Gains'!G2<=0, 0, MAX(0, L2 - S2)) -> 217914 | U2: =IF(T2<=0, 0, IF((O2+T2)<=Assumptions!$B$46, 0, IF(O2>=Assumptions!$B$46, T2*Assumptions!$C$46, (O2+T2-Assumptions!$B$46)*Assumptions!$C$46))) -> 0 | V2: =IF(M2<=250000, 0, 0.038 * MIN(M2 - 250000, D2 + T2)) -> 5677.5376 | W2: =P2 + U2 + V2 -> 7544.2926 | X2: =C2 + D2 + E2 + 'Capital Gains'!F2 -> 590646 | Y2: =IF(MAX(0, X2 - 20500)<=0, 0, IF(MAX(0, X2 - 20500)<=Assumptions!$B$20, MAX(0, X2 - 20500)*Assumptions!$C$19, IF(MAX(0, X2 - 20500)<=Assumptions!$B$21, Assumptions!$D$20 + (MAX(0, X2 - 20500)-Assumptions!$B$20)*Assumptions!$C$20, IF(MAX(0, X2 - 20500)<=Assumptions!$B$22, Assumptions!$D$21 + (MAX(0, X2 - 20500)-Assumptions!$B$21)*Assumptions!$C$21, IF(MAX(0, X2 - 20500)<=Assumptions!$B$23, Assumptions!$D$22 + (MAX(0, X2 - 20500)-Assumptions!$B$22)*Assumptions!$C$22, IF(MAX(0, X2 - 20500)<=Assumptions!$B$24, Assumptions!$D$23 + (MAX(0, X2 - 20500)-Assumptions!$B$23)*Assumptions!$C$23, IF(MAX(0, X2 - 20500)<=Assumptions!$B$25, Assumptions!$D$24 + (MAX(0, X2 - 20500)-Assumptions!$B$25)*Assumptions!$C$24, Assumptions!$D$25 + (MAX(0, X2 - 20500)-Assumptions!$B$25)*Assumptions!$C$25))))))) -> 32275.8 | Z2: =W2 + Y2 -> 39820.093 | AA2: =H2 + MIN(J2, 'Capital Gains'!F2) -> 218505.12
A3: 2027 | B3: ='Outside Income'!D3 * 0.85 -> 42840 | C3: ='Outside Income'!E3 -> 33717.133 | D3: =IF('Capital Gains'!G3<=0, 0, 'Outside Income'!G3) -> 17049.305 | E3: ='Inherited and Roth IRA'!K3 -> 200000 | F3: =IF('Capital Gains'!F3<=0, 0, MIN(MAX(0, 'Schedule A'!P3 - D3), 'Capital Gains'!F3)) -> 59573.491 | G3: =B3 + C3 + D3 + E3 + F3 -> 353179.93 | H3: =MAX(0, MIN(400000, G3 - ((20000 + 'Schedule A'!J3 + 'Schedule A'!K3 + 'Schedule A'!L3 + 'Schedule A'!Q3 + 'Schedule A'!C3 - 0.075 * MAX(0, K3 - F3)) / 1.075))) -> 165630.35 | I3: =MAX(0, G3 - H3) -> 187549.58 | J3: =MAX(0, 400000 - G3) -> 46820.071 | K3: =IF('Capital Gains'!G3<=0, 0, MAX(0, 'Capital Gains'!F3 - F3)) -> 0 | L3: =IF('Capital Gains'!G3<=0, 0, MAX(0, K3 - J3)) -> 0 | M3: =I3 + L3 -> 187549.58 | N3: ='Schedule A'!M3 -> 167549.58 | O3: =MAX(0, I3 - N3) -> 20000 | P3: =IF(O3<=0, 0, IF(O3<=Assumptions!$B$30, O3*Assumptions!$C$29, IF(O3<=Assumptions!$B$31, Assumptions!$D$30 + (O3-Assumptions!$B$30)*Assumptions!$C$30, IF(O3<=Assumptions!$B$32, Assumptions!$D$31 + (O3-Assumptions!$B$31)*Assumptions!$C$31, IF(O3<=Assumptions!$B$33, Assumptions!$D$32 + (O3-Assumptions!$B$32)*Assumptions!$C$32, IF(O3<=Assumptions!$B$34, Assumptions!$D$33 + (O3-Assumptions!$B$33)*Assumptions!$C$33, IF(O3<=Assumptions!$B$35, Assumptions!$D$34 + (O3-Assumptions!$B$34)*Assumptions!$C$34, Assumptions!$D$35 + (O3-Assumptions!$B$35)*Assumptions!$C$35))))))) -> 2000 | Q3: =L3 -> 0 | R3: =IF('Capital Gains'!G3<=0, 0, MIN('Schedule A'!R3, L3)) -> 0 | S3: =MAX(0, N3 - I3) -> 0 | T3: =IF('Capital Gains'!G3<=0, 0, MAX(0, L3 - S3)) -> 0 | U3: =IF(T3<=0, 0, IF((O3+T3)<=Assumptions!$B$46, 0, IF(O3>=Assumptions!$B$46, T3*Assumptions!$C$46, (O3+T3-Assumptions!$B$46)*Assumptions!$C$46))) -> 0 | V3: =IF(M3<=250000, 0, 0.038 * MIN(M3 - 250000, D3 + T3)) -> 0 | W3: =P3 + U3 + V3 -> 2000 | X3: =C3 + D3 + E3 + 'Capital Gains'!F3 -> 310339.93 | Y3: =IF(MAX(0, X3 - 20500)<=0, 0, IF(MAX(0, X3 - 20500)<=Assumptions!$B$20, MAX(0, X3 - 20500)*Assumptions!$C$19, IF(MAX(0, X3 - 20500)<=Assumptions!$B$21, Assumptions!$D$20 + (MAX(0, X3 - 20500)-Assumptions!$B$20)*Assumptions!$C$20, IF(MAX(0, X3 - 20500)<=Assumptions!$B$22, Assumptions!$D$21 + (MAX(0, X3 - 20500)-Assumptions!$B$21)*Assumptions!$C$21, IF(MAX(0, X3 - 20500)<=Assumptions!$B$23, Assumptions!$D$22 + (MAX(0, X3 - 20500)-Assumptions!$B$22)*Assumptions!$C$22, IF(MAX(0, X3 - 20500)<=Assumptions!$B$24, Assumptions!$D$23 + (MAX(0, X3 - 20500)-Assumptions!$B$23)*Assumptions!$C$23, IF(MAX(0, X3 - 20500)<=Assumptions!$B$25, Assumptions!$D$24 + (MAX(0, X3 - 20500)-Assumptions!$B$25)*Assumptions!$C$24, Assumptions!$D$25 + (MAX(0, X3 - 20500)-Assumptions!$B$25)*Assumptions!$C$25))))))) -> 14420.303 | Z3: =W3 + Y3 -> 16420.303 | AA3: =H3 + MIN(J3, 'Capital Gains'!F3) -> 212450.42
A4: 2028 | B4: ='Outside Income'!D4 * 0.85 -> 43268.4 | C4: ='Outside Income'!E4 -> 37088.846 | D4: =IF('Capital Gains'!G4<=0, 0, 'Outside Income'!G4) -> 16872.898 | E4: ='Inherited and Roth IRA'!K4 -> 200000 | F4: =IF('Capital Gains'!F4<=0, 0, MIN(MAX(0, 'Schedule A'!P4 - D4), 'Capital Gains'!F4)) -> 99433.903 | G4: =B4 + C4 + D4 + E4 + F4 -> 396664.05 | H4: =MAX(0, MIN(400000, G4 - ((20000 + 'Schedule A'!J4 + 'Schedule A'!K4 + 'Schedule A'!L4 + 'Schedule A'!Q4 + 'Schedule A'!C4 - 0.075 * MAX(0, K4 - F4)) / 1.075))) -> 172199.12 | I4: =MAX(0, G4 - H4) -> 224464.93 | J4: =MAX(0, 400000 - G4) -> 3335.9531 | K4: =IF('Capital Gains'!G4<=0, 0, MAX(0, 'Capital Gains'!F4 - F4)) -> 0 | L4: =IF('Capital Gains'!G4<=0, 0, MAX(0, K4 - J4)) -> 0 | M4: =I4 + L4 -> 224464.93 | N4: ='Schedule A'!M4 -> 204464.93 | O4: =MAX(0, I4 - N4) -> 20000 | P4: =IF(O4<=0, 0, IF(O4<=Assumptions!$B$30, O4*Assumptions!$C$29, IF(O4<=Assumptions!$B$31, Assumptions!$D$30 + (O4-Assumptions!$B$30)*Assumptions!$C$30, IF(O4<=Assumptions!$B$32, Assumptions!$D$31 + (O4-Assumptions!$B$31)*Assumptions!$C$31, IF(O4<=Assumptions!$B$33, Assumptions!$D$32 + (O4-Assumptions!$B$32)*Assumptions!$C$32, IF(O4<=Assumptions!$B$34, Assumptions!$D$33 + (O4-Assumptions!$B$33)*Assumptions!$C$33, IF(O4<=Assumptions!$B$35, Assumptions!$D$34 + (O4-Assumptions!$B$34)*Assumptions!$C$34, Assumptions!$D$35 + (O4-Assumptions!$B$35)*Assumptions!$C$35))))))) -> 2000 | Q4: =L4 -> 0 | R4: =IF('Capital Gains'!G4<=0, 0, MIN('Schedule A'!R4, L4)) -> 0 | S4: =MAX(0, N4 - I4) -> 0 | T4: =IF('Capital Gains'!G4<=0, 0, MAX(0, L4 - S4)) -> 0 | U4: =IF(T4<=0, 0, IF((O4+T4)<=Assumptions!$B$46, 0, IF(O4>=Assumptions!$B$46, T4*Assumptions!$C$46, (O4+T4-Assumptions!$B$46)*Assumptions!$C$46))) -> 0 | V4: =IF(M4<=250000, 0, 0.038 * MIN(M4 - 250000, D4 + T4)) -> 0 | W4: =P4 + U4 + V4 -> 2000 | X4: =C4 + D4 + E4 + 'Capital Gains'!F4 -> 353395.65 | Y4: =IF(MAX(0, X4 - 20500)<=0, 0, IF(MAX(0, X4 - 20500)<=Assumptions!$B$20, MAX(0, X4 - 20500)*Assumptions!$C$19, IF(MAX(0, X4 - 20500)<=Assumptions!$B$21, Assumptions!$D$20 + (MAX(0, X4 - 20500)-Assumptions!$B$20)*Assumptions!$C$20, IF(MAX(0, X4 - 20500)<=Assumptions!$B$22, Assumptions!$D$21 + (MAX(0, X4 - 20500)-Assumptions!$B$21)*Assumptions!$C$21, IF(MAX(0, X4 - 20500)<=Assumptions!$B$23, Assumptions!$D$22 + (MAX(0, X4 - 20500)-Assumptions!$B$22)*Assumptions!$C$22, IF(MAX(0, X4 - 20500)<=Assumptions!$B$24, Assumptions!$D$23 + (MAX(0, X4 - 20500)-Assumptions!$B$23)*Assumptions!$C$23, IF(MAX(0, X4 - 20500)<=Assumptions!$B$25, Assumptions!$D$24 + (MAX(0, X4 - 20500)-Assumptions!$B$25)*Assumptions!$C$24, Assumptions!$D$25 + (MAX(0, X4 - 20500)-Assumptions!$B$25)*Assumptions!$C$25))))))) -> 17162.953 | Z4: =W4 + Y4 -> 19162.953 | AA4: =H4 + MIN(J4, 'Capital Gains'!F4) -> 175535.07
A5: 2029 | B5: ='Outside Income'!D5 * 0.85 -> 43701.084 | C5: ='Outside Income'!E5 -> 40797.731 | D5: =IF('Capital Gains'!G5<=0, 0, 'Outside Income'!G5) -> 16609.67 | E5: ='Inherited and Roth IRA'!K5 -> 200000 | F5: =IF('Capital Gains'!F5<=0, 0, MIN(MAX(0, 'Schedule A'!P5 - D5), 'Capital Gains'!F5)) -> 104145.73 | G5: =B5 + C5 + D5 + E5 + F5 -> 405254.21 | H5: =MAX(0, MIN(400000, G5 - ((20000 + 'Schedule A'!J5 + 'Schedule A'!K5 + 'Schedule A'!L5 + 'Schedule A'!Q5 + 'Schedule A'!C5 - 0.075 * MAX(0, K5 - F5)) / 1.075))) -> 176651.05 | I5: =MAX(0, G5 - H5) -> 228603.16 | J5: =MAX(0, 400000 - G5) -> 0 | K5: =IF('Capital Gains'!G5<=0, 0, MAX(0, 'Capital Gains'!F5 - F5)) -> 33743.91 | L5: =IF('Capital Gains'!G5<=0, 0, MAX(0, K5 - J5)) -> 33743.91 | M5: =I5 + L5 -> 262347.07 | N5: ='Schedule A'!M5 -> 206072.37 | O5: =MAX(0, I5 - N5) -> 22530.793 | P5: =IF(O5<=0, 0, IF(O5<=Assumptions!$B$30, O5*Assumptions!$C$29, IF(O5<=Assumptions!$B$31, Assumptions!$D$30 + (O5-Assumptions!$B$30)*Assumptions!$C$30, IF(O5<=Assumptions!$B$32, Assumptions!$D$31 + (O5-Assumptions!$B$31)*Assumptions!$C$31, IF(O5<=Assumptions!$B$33, Assumptions!$D$32 + (O5-Assumptions!$B$32)*Assumptions!$C$32, IF(O5<=Assumptions!$B$34, Assumptions!$D$33 + (O5-Assumptions!$B$33)*Assumptions!$C$33, IF(O5<=Assumptions!$B$35, Assumptions!$D$34 + (O5-Assumptions!$B$34)*Assumptions!$C$34, Assumptions!$D$35 + (O5-Assumptions!$B$35)*Assumptions!$C$35))))))) -> 2253.0793 | Q5: =L5 -> 33743.91 | R5: =IF('Capital Gains'!G5<=0, 0, MIN('Schedule A'!R5, L5)) -> 0 | S5: =MAX(0, N5 - I5) -> 0 | T5: =IF('Capital Gains'!G5<=0, 0, MAX(0, L5 - S5)) -> 33743.91 | U5: =IF(T5<=0, 0, IF((O5+T5)<=Assumptions!$B$46, 0, IF(O5>=Assumptions!$B$46, T5*Assumptions!$C$46, (O5+T5-Assumptions!$B$46)*Assumptions!$C$46))) -> 0 | V5: =IF(M5<=250000, 0, 0.038 * MIN(M5 - 250000, D5 + T5)) -> 469.18871 | W5: =P5 + U5 + V5 -> 2722.268 | X5: =C5 + D5 + E5 + 'Capital Gains'!F5 -> 395297.04 | Y5: =IF(MAX(0, X5 - 20500)<=0, 0, IF(MAX(0, X5 - 20500)<=Assumptions!$B$20, MAX(0, X5 - 20500)*Assumptions!$C$19, IF(MAX(0, X5 - 20500)<=Assumptions!$B$21, Assumptions!$D$20 + (MAX(0, X5 - 20500)-Assumptions!$B$20)*Assumptions!$C$20, IF(MAX(0, X5 - 20500)<=Assumptions!$B$22, Assumptions!$D$21 + (MAX(0, X5 - 20500)-Assumptions!$B$21)*Assumptions!$C$21, IF(MAX(0, X5 - 20500)<=Assumptions!$B$23, Assumptions!$D$22 + (MAX(0, X5 - 20500)-Assumptions!$B$22)*Assumptions!$C$22, IF(MAX(0, X5 - 20500)<=Assumptions!$B$24, Assumptions!$D$23 + (MAX(0, X5 - 20500)-Assumptions!$B$23)*Assumptions!$C$23, IF(MAX(0, X5 - 20500)<=Assumptions!$B$25, Assumptions!$D$24 + (MAX(0, X5 - 20500)-Assumptions!$B$25)*Assumptions!$C$24, Assumptions!$D$25 + (MAX(0, X5 - 20500)-Assumptions!$B$25)*Assumptions!$C$25))))))) -> 19832.071 | Z5: =W5 + Y5 -> 22554.339 | AA5: =H5 + MIN(J5, 'Capital Gains'!F5) -> 176651.05
A6: 2030 | B6: ='Outside Income'!D6 * 0.85 -> 44138.095 | C6: ='Outside Income'!E6 -> 44877.504 | D6: =IF('Capital Gains'!G6<=0, 0, 'Outside Income'!G6) -> 16249.129 | E6: ='Inherited and Roth IRA'!K6 -> 200000 | F6: =IF('Capital Gains'!F6<=0, 0, MIN(MAX(0, 'Schedule A'!P6 - D6), 'Capital Gains'!F6)) -> 107673.62 | G6: =B6 + C6 + D6 + E6 + F6 -> 412938.35 | H6: =MAX(0, MIN(400000, G6 - ((20000 + 'Schedule A'!J6 + 'Schedule A'!K6 + 'Schedule A'!L6 + 'Schedule A'!Q6 + 'Schedule A'!C6 - 0.075 * MAX(0, K6 - F6)) / 1.075))) -> 181388.81 | I6: =MAX(0, G6 - H6) -> 231549.53 | J6: =MAX(0, 400000 - G6) -> 0 | K6: =IF('Capital Gains'!G6<=0, 0, MAX(0, 'Capital Gains'!F6 - F6)) -> 67339.138 | L6: =IF('Capital Gains'!G6<=0, 0, MAX(0, K6 - J6)) -> 67339.138 | M6: =I6 + L6 -> 298888.67 | N6: ='Schedule A'!M6 -> 206499.1 | O6: =MAX(0, I6 - N6) -> 25050.435 | P6: =IF(O6<=0, 0, IF(O6<=Assumptions!$B$30, O6*Assumptions!$C$29, IF(O6<=Assumptions!$B$31, Assumptions!$D$30 + (O6-Assumptions!$B$30)*Assumptions!$C$30, IF(O6<=Assumptions!$B$32, Assumptions!$D$31 + (O6-Assumptions!$B$31)*Assumptions!$C$31, IF(O6<=Assumptions!$B$33, Assumptions!$D$32 + (O6-Assumptions!$B$32)*Assumptions!$C$32, IF(O6<=Assumptions!$B$34, Assumptions!$D$33 + (O6-Assumptions!$B$33)*Assumptions!$C$33, IF(O6<=Assumptions!$B$35, Assumptions!$D$34 + (O6-Assumptions!$B$34)*Assumptions!$C$34, Assumptions!$D$35 + (O6-Assumptions!$B$35)*Assumptions!$C$35))))))) -> 2542.0522 | Q6: =L6 -> 67339.138 | R6: =IF('Capital Gains'!G6<=0, 0, MIN('Schedule A'!R6, L6)) -> 0 | S6: =MAX(0, N6 - I6) -> 0 | T6: =IF('Capital Gains'!G6<=0, 0, MAX(0, L6 - S6)) -> 67339.138 | U6: =IF(T6<=0, 0, IF((O6+T6)<=Assumptions!$B$46, 0, IF(O6>=Assumptions!$B$46, T6*Assumptions!$C$46, (O6+T6-Assumptions!$B$46)*Assumptions!$C$46))) -> 0 | V6: =IF(M6<=250000, 0, 0.038 * MIN(M6 - 250000, D6 + T6)) -> 1857.7696 | W6: =P6 + U6 + V6 -> 4399.8218 | X6: =C6 + D6 + E6 + 'Capital Gains'!F6 -> 436139.39 | Y6: =IF(MAX(0, X6 - 20500)<=0, 0, IF(MAX(0, X6 - 20500)<=Assumptions!$B$20, MAX(0, X6 - 20500)*Assumptions!$C$19, IF(MAX(0, X6 - 20500)<=Assumptions!$B$21, Assumptions!$D$20 + (MAX(0, X6 - 20500)-Assumptions!$B$20)*Assumptions!$C$20, IF(MAX(0, X6 - 20500)<=Assumptions!$B$22, Assumptions!$D$21 + (MAX(0, X6 - 20500)-Assumptions!$B$21)*Assumptions!$C$21, IF(MAX(0, X6 - 20500)<=Assumptions!$B$23, Assumptions!$D$22 + (MAX(0, X6 - 20500)-Assumptions!$B$22)*Assumptions!$C$22, IF(MAX(0, X6 - 20500)<=Assumptions!$B$24, Assumptions!$D$23 + (MAX(0, X6 - 20500)-Assumptions!$B$23)*Assumptions!$C$23, IF(MAX(0, X6 - 20500)<=Assumptions!$B$25, Assumptions!$D$24 + (MAX(0, X6 - 20500)-Assumptions!$B$25)*Assumptions!$C$24, Assumptions!$D$25 + (MAX(0, X6 - 20500)-Assumptions!$B$25)*Assumptions!$C$25))))))) -> 22433.729 | Z6: =W6 + Y6 -> 26833.551 | AA6: =H6 + MIN(J6, 'Capital Gains'!F6) -> 181388.81
A7: 2031 | B7: ='Outside Income'!D7 * 0.85 -> 44579.476 | C7: ='Outside Income'!E7 -> 49365.255 | D7: =IF('Capital Gains'!G7<=0, 0, 'Outside Income'!G7) -> 15779.708 | E7: ='Inherited and Roth IRA'!K7 -> 200000 | F7: =IF('Capital Gains'!F7<=0, 0, MIN(MAX(0, 'Schedule A'!P7 - D7), 'Capital Gains'!F7)) -> 119296.09 | G7: =B7 + C7 + D7 + E7 + F7 -> 429020.53 | H7: =MAX(0, MIN(400000, G7 - ((20000 + 'Schedule A'!J7 + 'Schedule A'!K7 + 'Schedule A'!L7 + 'Schedule A'!Q7 + 'Schedule A'!C7 - 0.075 * MAX(0, K7 - F7)) / 1.075))) -> 187096.07 | I7: =MAX(0, G7 - H7) -> 241924.46 | J7: =MAX(0, 400000 - G7) -> 0 | K7: =IF('Capital Gains'!G7<=0, 0, MAX(0, 'Capital Gains'!F7 - F7)) -> 91572.412 | L7: =IF('Capital Gains'!G7<=0, 0, MAX(0, K7 - J7)) -> 91572.412 | M7: =I7 + L7 -> 333496.87 | N7: ='Schedule A'!M7 -> 215056.53 | O7: =MAX(0, I7 - N7) -> 26867.931 | P7: =IF(O7<=0, 0, IF(O7<=Assumptions!$B$30, O7*Assumptions!$C$29, IF(O7<=Assumptions!$B$31, Assumptions!$D$30 + (O7-Assumptions!$B$30)*Assumptions!$C$30, IF(O7<=Assumptions!$B$32, Assumptions!$D$31 + (O7-Assumptions!$B$31)*Assumptions!$C$31, IF(O7<=Assumptions!$B$33, Assumptions!$D$32 + (O7-Assumptions!$B$32)*Assumptions!$C$32, IF(O7<=Assumptions!$B$34, Assumptions!$D$33 + (O7-Assumptions!$B$33)*Assumptions!$C$33, IF(O7<=Assumptions!$B$35, Assumptions!$D$34 + (O7-Assumptions!$B$34)*Assumptions!$C$34, Assumptions!$D$35 + (O7-Assumptions!$B$35)*Assumptions!$C$35))))))) -> 2760.1517 | Q7: =L7 -> 91572.412 | R7: =IF('Capital Gains'!G7<=0, 0, MIN('Schedule A'!R7, L7)) -> 0 | S7: =MAX(0, N7 - I7) -> 0 | T7: =IF('Capital Gains'!G7<=0, 0, MAX(0, L7 - S7)) -> 91572.412 | U7: =IF(T7<=0, 0, IF((O7+T7)<=Assumptions!$B$46, 0, IF(O7>=Assumptions!$B$46, T7*Assumptions!$C$46, (O7+T7-Assumptions!$B$46)*Assumptions!$C$46))) -> 0 | V7: =IF(M7<=250000, 0, 0.038 * MIN(M7 - 250000, D7 + T7)) -> 3172.8812 | W7: =P7 + U7 + V7 -> 5933.0329 | X7: =C7 + D7 + E7 + 'Capital Gains'!F7 -> 476013.46 | Y7: =IF(MAX(0, X7 - 20500)<=0, 0, IF(MAX(0, X7 - 20500)<=Assumptions!$B$20, MAX(0, X7 - 20500)*Assumptions!$C$19, IF(MAX(0, X7 - 20500)<=Assumptions!$B$21, Assumptions!$D$20 + (MAX(0, X7 - 20500)-Assumptions!$B$20)*Assumptions!$C$20, IF(MAX(0, X7 - 20500)<=Assumptions!$B$22, Assumptions!$D$21 + (MAX(0, X7 - 20500)-Assumptions!$B$21)*Assumptions!$C$21, IF(MAX(0, X7 - 20500)<=Assumptions!$B$23, Assumptions!$D$22 + (MAX(0, X7 - 20500)-Assumptions!$B$22)*Assumptions!$C$22, IF(MAX(0, X7 - 20500)<=Assumptions!$B$24, Assumptions!$D$23 + (MAX(0, X7 - 20500)-Assumptions!$B$23)*Assumptions!$C$23, IF(MAX(0, X7 - 20500)<=Assumptions!$B$25, Assumptions!$D$24 + (MAX(0, X7 - 20500)-Assumptions!$B$25)*Assumptions!$C$24, Assumptions!$D$25 + (MAX(0, X7 - 20500)-Assumptions!$B$25)*Assumptions!$C$25))))))) -> 24973.708 | Z7: =W7 + Y7 -> 30906.741 | AA7: =H7 + MIN(J7, 'Capital Gains'!F7) -> 187096.07
A8: 2032 | B8: ='Outside Income'!D8 * 0.85 -> 45025.271 | C8: ='Outside Income'!E8 -> 54301.78 | D8: =IF('Capital Gains'!G8<=0, 0, 'Outside Income'!G8) -> 15188.669 | E8: ='Inherited and Roth IRA'!K8 -> 144757.17 | F8: =IF('Capital Gains'!F8<=0, 0, MIN(MAX(0, 'Schedule A'!P8 - D8), 'Capital Gains'!F8)) -> 132043.95 | G8: =B8 + C8 + D8 + E8 + F8 -> 391316.83 | H8: =MAX(0, MIN(400000, G8 - ((20000 + 'Schedule A'!J8 + 'Schedule A'!K8 + 'Schedule A'!L8 + 'Schedule A'!Q8 + 'Schedule A'!C8 - 0.075 * MAX(0, K8 - F8)) / 1.075))) -> 138083.7 | I8: =MAX(0, G8 - H8) -> 253233.13 | J8: =MAX(0, 400000 - G8) -> 8683.1651 | K8: =IF('Capital Gains'!G8<=0, 0, MAX(0, 'Capital Gains'!F8 - F8)) -> 113471.04 | L8: =IF('Capital Gains'!G8<=0, 0, MAX(0, K8 - J8)) -> 104787.87 | M8: =I8 + L8 -> 358021.01 | N8: ='Schedule A'!M8 -> 225374.04 | O8: =MAX(0, I8 - N8) -> 27859.091 | P8: =IF(O8<=0, 0, IF(O8<=Assumptions!$B$30, O8*Assumptions!$C$29, IF(O8<=Assumptions!$B$31, Assumptions!$D$30 + (O8-Assumptions!$B$30)*Assumptions!$C$30, IF(O8<=Assumptions!$B$32, Assumptions!$D$31 + (O8-Assumptions!$B$31)*Assumptions!$C$31, IF(O8<=Assumptions!$B$33, Assumptions!$D$32 + (O8-Assumptions!$B$32)*Assumptions!$C$32, IF(O8<=Assumptions!$B$34, Assumptions!$D$33 + (O8-Assumptions!$B$33)*Assumptions!$C$33, IF(O8<=Assumptions!$B$35, Assumptions!$D$34 + (O8-Assumptions!$B$34)*Assumptions!$C$34, Assumptions!$D$35 + (O8-Assumptions!$B$35)*Assumptions!$C$35))))))) -> 2879.0909 | Q8: =L8 -> 104787.87 | R8: =IF('Capital Gains'!G8<=0, 0, MIN('Schedule A'!R8, L8)) -> 0 | S8: =MAX(0, N8 - I8) -> 0 | T8: =IF('Capital Gains'!G8<=0, 0, MAX(0, L8 - S8)) -> 104787.87 | U8: =IF(T8<=0, 0, IF((O8+T8)<=Assumptions!$B$46, 0, IF(O8>=Assumptions!$B$46, T8*Assumptions!$C$46, (O8+T8-Assumptions!$B$46)*Assumptions!$C$46))) -> 0 | V8: =IF(M8<=250000, 0, 0.038 * MIN(M8 - 250000, D8 + T8)) -> 4104.7983 | W8: =P8 + U8 + V8 -> 6983.8892 | X8: =C8 + D8 + E8 + 'Capital Gains'!F8 -> 459762.6 | Y8: =IF(MAX(0, X8 - 20500)<=0, 0, IF(MAX(0, X8 - 20500)<=Assumptions!$B$20, MAX(0, X8 - 20500)*Assumptions!$C$19, IF(MAX(0, X8 - 20500)<=Assumptions!$B$21, Assumptions!$D$20 + (MAX(0, X8 - 20500)-Assumptions!$B$20)*Assumptions!$C$20, IF(MAX(0, X8 - 20500)<=Assumptions!$B$22, Assumptions!$D$21 + (MAX(0, X8 - 20500)-Assumptions!$B$21)*Assumptions!$C$21, IF(MAX(0, X8 - 20500)<=Assumptions!$B$23, Assumptions!$D$22 + (MAX(0, X8 - 20500)-Assumptions!$B$22)*Assumptions!$C$22, IF(MAX(0, X8 - 20500)<=Assumptions!$B$24, Assumptions!$D$23 + (MAX(0, X8 - 20500)-Assumptions!$B$23)*Assumptions!$C$23, IF(MAX(0, X8 - 20500)<=Assumptions!$B$25, Assumptions!$D$24 + (MAX(0, X8 - 20500)-Assumptions!$B$25)*Assumptions!$C$24, Assumptions!$D$25 + (MAX(0, X8 - 20500)-Assumptions!$B$25)*Assumptions!$C$25))))))) -> 23938.528 | Z8: =W8 + Y8 -> 30922.417 | AA8: =H8 + MIN(J8, 'Capital Gains'!F8) -> 146766.87
A9: 2033 | B9: ='Outside Income'!D9 * 0.85 -> 45475.523 | C9: ='Outside Income'!E9 -> 59731.958 | D9: =IF('Capital Gains'!G9<=0, 0, 'Outside Income'!G9) -> 14461.984 | E9: ='Inherited and Roth IRA'!K9 -> 0 | F9: =IF('Capital Gains'!F9<=0, 0, MIN(MAX(0, 'Schedule A'!P9 - D9), 'Capital Gains'!F9)) -> 146021.57 | G9: =B9 + C9 + D9 + E9 + F9 -> 265691.04 | H9: 0 | I9: =MAX(0, G9 - H9) -> 265691.04 | J9: 0 | K9: =IF('Capital Gains'!G9<=0, 0, MAX(0, 'Capital Gains'!F9 - F9)) -> 132981.37 | L9: =IF('Capital Gains'!G9<=0, 0, MAX(0, K9 - J9)) -> 132981.37 | M9: =I9 + L9 -> 398672.41 | N9: ='Schedule A'!M9 -> 235576.12 | O9: =MAX(0, I9 - N9) -> 30114.912 | P9: =IF(O9<=0, 0, IF(O9<=Assumptions!$B$30, O9*Assumptions!$C$29, IF(O9<=Assumptions!$B$31, Assumptions!$D$30 + (O9-Assumptions!$B$30)*Assumptions!$C$30, IF(O9<=Assumptions!$B$32, Assumptions!$D$31 + (O9-Assumptions!$B$31)*Assumptions!$C$31, IF(O9<=Assumptions!$B$33, Assumptions!$D$32 + (O9-Assumptions!$B$32)*Assumptions!$C$32, IF(O9<=Assumptions!$B$34, Assumptions!$D$33 + (O9-Assumptions!$B$33)*Assumptions!$C$33, IF(O9<=Assumptions!$B$35, Assumptions!$D$34 + (O9-Assumptions!$B$34)*Assumptions!$C$34, Assumptions!$D$35 + (O9-Assumptions!$B$35)*Assumptions!$C$35))))))) -> 3149.7894 | Q9: =L9 -> 132981.37 | R9: =IF('Capital Gains'!G9<=0, 0, MIN('Schedule A'!R9, L9)) -> 0 | S9: =MAX(0, N9 - I9) -> 0 | T9: =IF('Capital Gains'!G9<=0, 0, MAX(0, L9 - S9)) -> 132981.37 | U9: =IF(T9<=0, 0, IF((O9+T9)<=Assumptions!$B$46, 0, IF(O9>=Assumptions!$B$46, T9*Assumptions!$C$46, (O9+T9-Assumptions!$B$46)*Assumptions!$C$46))) -> 0 | V9: =IF(M9<=250000, 0, 0.038 * MIN(M9 - 250000, D9 + T9)) -> 5602.8476 | W9: =P9 + U9 + V9 -> 8752.637 | X9: =C9 + D9 + E9 + 'Capital Gains'!F9 -> 353196.89 | Y9: =IF(MAX(0, X9 - 20500)<=0, 0, IF(MAX(0, X9 - 20500)<=Assumptions!$B$20, MAX(0, X9 - 20500)*Assumptions!$C$19, IF(MAX(0, X9 - 20500)<=Assumptions!$B$21, Assumptions!$D$20 + (MAX(0, X9 - 20500)-Assumptions!$B$20)*Assumptions!$C$20, IF(MAX(0, X9 - 20500)<=Assumptions!$B$22, Assumptions!$D$21 + (MAX(0, X9 - 20500)-Assumptions!$B$21)*Assumptions!$C$21, IF(MAX(0, X9 - 20500)<=Assumptions!$B$23, Assumptions!$D$22 + (MAX(0, X9 - 20500)-Assumptions!$B$22)*Assumptions!$C$22, IF(MAX(0, X9 - 20500)<=Assumptions!$B$24, Assumptions!$D$23 + (MAX(0, X9 - 20500)-Assumptions!$B$23)*Assumptions!$C$23, IF(MAX(0, X9 - 20500)<=Assumptions!$B$25, Assumptions!$D$24 + (MAX(0, X9 - 20500)-Assumptions!$B$25)*Assumptions!$C$24, Assumptions!$D$25 + (MAX(0, X9 - 20500)-Assumptions!$B$25)*Assumptions!$C$25))))))) -> 17150.292 | Z9: =W9 + Y9 -> 25902.929 | AA9: =H9 + MIN(J9, 'Capital Gains'!F9) -> 0
A10: 2034 | B10: ='Outside Income'!D10 * 0.85 -> 45930.278 | C10: ='Outside Income'!E10 -> 65705.154 | D10: =IF('Capital Gains'!G10<=0, 0, 'Outside Income'!G10) -> 13584.213 | E10: ='Inherited and Roth IRA'!K10 -> 0 | F10: =IF('Capital Gains'!F10<=0, 0, MIN(MAX(0, 'Schedule A'!P10 - D10), 'Capital Gains'!F10)) -> 161342.86 | G10: =B10 + C10 + D10 + E10 + F10 -> 286562.51 | H10: 0 | I10: =MAX(0, G10 - H10) -> 286562.51 | J10: 0 | K10: =IF('Capital Gains'!G10<=0, 0, MAX(0, 'Capital Gains'!F10 - F10)) -> 150032.5 | L10: =IF('Capital Gains'!G10<=0, 0, MAX(0, K10 - J10)) -> 150032.5 | M10: =I10 + L10 -> 436595.01 | N10: ='Schedule A'!M10 -> 247175.45 | O10: =MAX(0, I10 - N10) -> 39387.058 | P10: =IF(O10<=0, 0, IF(O10<=Assumptions!$B$30, O10*Assumptions!$C$29, IF(O10<=Assumptions!$B$31, Assumptions!$D$30 + (O10-Assumptions!$B$30)*Assumptions!$C$30, IF(O10<=Assumptions!$B$32, Assumptions!$D$31 + (O10-Assumptions!$B$31)*Assumptions!$C$31, IF(O10<=Assumptions!$B$33, Assumptions!$D$32 + (O10-Assumptions!$B$32)*Assumptions!$C$32, IF(O10<=Assumptions!$B$34, Assumptions!$D$33 + (O10-Assumptions!$B$33)*Assumptions!$C$33, IF(O10<=Assumptions!$B$35, Assumptions!$D$34 + (O10-Assumptions!$B$34)*Assumptions!$C$34, Assumptions!$D$35 + (O10-Assumptions!$B$35)*Assumptions!$C$35))))))) -> 4262.447 | Q10: =L10 -> 150032.5 | R10: =IF('Capital Gains'!G10<=0, 0, MIN('Schedule A'!R10, L10)) -> 0 | S10: =MAX(0, N10 - I10) -> 0 | T10: =IF('Capital Gains'!G10<=0, 0, MAX(0, L10 - S10)) -> 150032.5 | U10: =IF(T10<=0, 0, IF((O10+T10)<=Assumptions!$B$46, 0, IF(O10>=Assumptions!$B$46, T10*Assumptions!$C$46, (O10+T10-Assumptions!$B$46)*Assumptions!$C$46))) -> 0 | V10: =IF(M10<=250000, 0, 0.038 * MIN(M10 - 250000, D10 + T10)) -> 6217.4351 | W10: =P10 + U10 + V10 -> 10479.882 | X10: =C10 + D10 + E10 + 'Capital Gains'!F10 -> 390664.73 | Y10: =IF(MAX(0, X10 - 20500)<=0, 0, IF(MAX(0, X10 - 20500)<=Assumptions!$B$20, MAX(0, X10 - 20500)*Assumptions!$C$19, IF(MAX(0, X10 - 20500)<=Assumptions!$B$21, Assumptions!$D$20 + (MAX(0, X10 - 20500)-Assumptions!$B$20)*Assumptions!$C$20, IF(MAX(0, X10 - 20500)<=Assumptions!$B$22, Assumptions!$D$21 + (MAX(0, X10 - 20500)-Assumptions!$B$21)*Assumptions!$C$21, IF(MAX(0, X10 - 20500)<=Assumptions!$B$23, Assumptions!$D$22 + (MAX(0, X10 - 20500)-Assumptions!$B$22)*Assumptions!$C$22, IF(MAX(0, X10 - 20500)<=Assumptions!$B$24, Assumptions!$D$23 + (MAX(0, X10 - 20500)-Assumptions!$B$23)*Assumptions!$C$23, IF(MAX(0, X10 - 20500)<=Assumptions!$B$25, Assumptions!$D$24 + (MAX(0, X10 - 20500)-Assumptions!$B$25)*Assumptions!$C$24, Assumptions!$D$25 + (MAX(0, X10 - 20500)-Assumptions!$B$25)*Assumptions!$C$25))))))) -> 19536.993 | Z10: =W10 + Y10 -> 30016.875 | AA10: =H10 + MIN(J10, 'Capital Gains'!F10) -> 0
A11: 2035 | B11: ='Outside Income'!D11 * 0.85 -> 46389.581 | C11: ='Outside Income'!E11 -> 72275.669 | D11: =IF('Capital Gains'!G11<=0, 0, 'Outside Income'!G11) -> 12538.364 | E11: ='Inherited and Roth IRA'!K11 -> 0 | F11: =IF('Capital Gains'!F11<=0, 0, MIN(MAX(0, 'Schedule A'!P11 - D11), 'Capital Gains'!F11)) -> 178132.15 | G11: =B11 + C11 + D11 + E11 + F11 -> 309335.76 | H11: 0 | I11: =MAX(0, G11 - H11) -> 309335.76 | J11: 0 | K11: =IF('Capital Gains'!G11<=0, 0, MAX(0, 'Capital Gains'!F11 - F11)) -> 164535.04 | L11: =IF('Capital Gains'!G11<=0, 0, MAX(0, K11 - J11)) -> 164535.04 | M11: =I11 + L11 -> 473870.8 | N11: ='Schedule A'!M11 -> 260123.2 | O11: =MAX(0, I11 - N11) -> 49212.56 | P11: =IF(O11<=0, 0, IF(O11<=Assumptions!$B$30, O11*Assumptions!$C$29, IF(O11<=Assumptions!$B$31, Assumptions!$D$30 + (O11-Assumptions!$B$30)*Assumptions!$C$30, IF(O11<=Assumptions!$B$32, Assumptions!$D$31 + (O11-Assumptions!$B$31)*Assumptions!$C$31, IF(O11<=Assumptions!$B$33, Assumptions!$D$32 + (O11-Assumptions!$B$32)*Assumptions!$C$32, IF(O11<=Assumptions!$B$34, Assumptions!$D$33 + (O11-Assumptions!$B$33)*Assumptions!$C$33, IF(O11<=Assumptions!$B$35, Assumptions!$D$34 + (O11-Assumptions!$B$34)*Assumptions!$C$34, Assumptions!$D$35 + (O11-Assumptions!$B$35)*Assumptions!$C$35))))))) -> 5441.5072 | Q11: =L11 -> 164535.04 | R11: =IF('Capital Gains'!G11<=0, 0, MIN('Schedule A'!R11, L11)) -> 0 | S11: =MAX(0, N11 - I11) -> 0 | T11: =IF('Capital Gains'!G11<=0, 0, MAX(0, L11 - S11)) -> 164535.04 | U11: =IF(T11<=0, 0, IF((O11+T11)<=Assumptions!$B$46, 0, IF(O11>=Assumptions!$B$46, T11*Assumptions!$C$46, (O11+T11-Assumptions!$B$46)*Assumptions!$C$46))) -> 0 | V11: =IF(M11<=250000, 0, 0.038 * MIN(M11 - 250000, D11 + T11)) -> 6728.7892 | W11: =P11 + U11 + V11 -> 12170.296 | X11: =C11 + D11 + E11 + 'Capital Gains'!F11 -> 427481.22 | Y11: =IF(MAX(0, X11 - 20500)<=0, 0, IF(MAX(0, X11 - 20500)<=Assumptions!$B$20, MAX(0, X11 - 20500)*Assumptions!$C$19, IF(MAX(0, X11 - 20500)<=Assumptions!$B$21, Assumptions!$D$20 + (MAX(0, X11 - 20500)-Assumptions!$B$20)*Assumptions!$C$20, IF(MAX(0, X11 - 20500)<=Assumptions!$B$22, Assumptions!$D$21 + (MAX(0, X11 - 20500)-Assumptions!$B$21)*Assumptions!$C$21, IF(MAX(0, X11 - 20500)<=Assumptions!$B$23, Assumptions!$D$22 + (MAX(0, X11 - 20500)-Assumptions!$B$22)*Assumptions!$C$22, IF(MAX(0, X11 - 20500)<=Assumptions!$B$24, Assumptions!$D$23 + (MAX(0, X11 - 20500)-Assumptions!$B$23)*Assumptions!$C$23, IF(MAX(0, X11 - 20500)<=Assumptions!$B$25, Assumptions!$D$24 + (MAX(0, X11 - 20500)-Assumptions!$B$25)*Assumptions!$C$24, Assumptions!$D$25 + (MAX(0, X11 - 20500)-Assumptions!$B$25)*Assumptions!$C$25))))))) -> 21882.203 | Z11: =W11 + Y11 -> 34052.5 | AA11: =H11 + MIN(J11, 'Capital Gains'!F11) -> 0
A12: 2036 | B12: ='Outside Income'!D12 * 0.85 -> 46853.477 | C12: ='Outside Income'!E12 -> 79503.236 | D12: =IF('Capital Gains'!G12<=0, 0, 'Outside Income'!G12) -> 11305.749 | E12: ='Inherited and Roth IRA'!K12 | F12: =IF('Capital Gains'!F12<=0, 0, MIN(MAX(0, 'Schedule A'!P12 - D12), 'Capital Gains'!F12)) -> 196525.11 | G12: =B12 + C12 + D12 + E12 + F12 -> 334187.57 | H12: 0 | I12: =MAX(0, G12 - H12) -> 334187.57 | J12: 0 | K12: =IF('Capital Gains'!G12<=0, 0, MAX(0, 'Capital Gains'!F12 - F12)) -> 176379.8 | L12: =IF('Capital Gains'!G12<=0, 0, MAX(0, K12 - J12)) -> 176379.8 | M12: =I12 + L12 -> 510567.37 | N12: ='Schedule A'!M12 -> 274531.3 | O12: =MAX(0, I12 - N12) -> 59656.266 | P12: =IF(O12<=0, 0, IF(O12<=Assumptions!$B$30, O12*Assumptions!$C$29, IF(O12<=Assumptions!$B$31, Assumptions!$D$30 + (O12-Assumptions!$B$30)*Assumptions!$C$30, IF(O12<=Assumptions!$B$32, Assumptions!$D$31 + (O12-Assumptions!$B$31)*Assumptions!$C$31, IF(O12<=Assumptions!$B$33, Assumptions!$D$32 + (O12-Assumptions!$B$32)*Assumptions!$C$32, IF(O12<=Assumptions!$B$34, Assumptions!$D$33 + (O12-Assumptions!$B$33)*Assumptions!$C$33, IF(O12<=Assumptions!$B$35, Assumptions!$D$34 + (O12-Assumptions!$B$34)*Assumptions!$C$34, Assumptions!$D$35 + (O12-Assumptions!$B$35)*Assumptions!$C$35))))))) -> 6694.7519 | Q12: =L12 -> 176379.8 | R12: =IF('Capital Gains'!G12<=0, 0, MIN('Schedule A'!R12, L12)) -> 0 | S12: =MAX(0, N12 - I12) -> 0 | T12: =IF('Capital Gains'!G12<=0, 0, MAX(0, L12 - S12)) -> 176379.8 | U12: =IF(T12<=0, 0, IF((O12+T12)<=Assumptions!$B$46, 0, IF(O12>=Assumptions!$B$46, T12*Assumptions!$C$46, (O12+T12-Assumptions!$B$46)*Assumptions!$C$46))) -> 0 | V12: =IF(M12<=250000, 0, 0.038 * MIN(M12 - 250000, D12 + T12)) -> 7132.0507 | W12: =P12 + U12 + V12 -> 13826.803 | X12: =C12 + D12 + E12 + 'Capital Gains'!F12 -> 463713.89 | Y12: =IF(MAX(0, X12 - 20500)<=0, 0, IF(MAX(0, X12 - 20500)<=Assumptions!$B$20, MAX(0, X12 - 20500)*Assumptions!$C$19, IF(MAX(0, X12 - 20500)<=Assumptions!$B$21, Assumptions!$D$20 + (MAX(0, X12 - 20500)-Assumptions!$B$20)*Assumptions!$C$20, IF(MAX(0, X12 - 20500)<=Assumptions!$B$22, Assumptions!$D$21 + (MAX(0, X12 - 20500)-Assumptions!$B$21)*Assumptions!$C$21, IF(MAX(0, X12 - 20500)<=Assumptions!$B$23, Assumptions!$D$22 + (MAX(0, X12 - 20500)-Assumptions!$B$22)*Assumptions!$C$22, IF(MAX(0, X12 - 20500)<=Assumptions!$B$24, Assumptions!$D$23 + (MAX(0, X12 - 20500)-Assumptions!$B$23)*Assumptions!$C$23, IF(MAX(0, X12 - 20500)<=Assumptions!$B$25, Assumptions!$D$24 + (MAX(0, X12 - 20500)-Assumptions!$B$25)*Assumptions!$C$24, Assumptions!$D$25 + (MAX(0, X12 - 20500)-Assumptions!$B$25)*Assumptions!$C$25))))))) -> 24190.225 | Z12: =W12 + Y12 -> 38017.027 | AA12: =H12 + MIN(J12, 'Capital Gains'!F12) -> 0
A13: 2037 | B13: ='Outside Income'!D13 * 0.85 -> 47322.012 | C13: ='Outside Income'!E13 -> 87453.56 | D13: =IF('Capital Gains'!G13<=0, 0, 'Outside Income'!G13) -> 9865.8146 | E13: ='Inherited and Roth IRA'!K13 | F13: =IF('Capital Gains'!F13<=0, 0, MIN(MAX(0, 'Schedule A'!P13 - D13), 'Capital Gains'!F13)) -> 216669.82 | G13: =B13 + C13 + D13 + E13 + F13 -> 361311.21 | H13: 0 | I13: =MAX(0, G13 - H13) -> 361311.21 | J13: 0 | K13: =IF('Capital Gains'!G13<=0, 0, MAX(0, 'Capital Gains'!F13 - F13)) -> 185436.36 | L13: =IF('Capital Gains'!G13<=0, 0, MAX(0, K13 - J13)) -> 185436.36 | M13: =I13 + L13 -> 546747.56 | N13: ='Schedule A'!M13 -> 290522.57 | O13: =MAX(0, I13 - N13) -> 70788.639 | P13: =IF(O13<=0, 0, IF(O13<=Assumptions!$B$30, O13*Assumptions!$C$29, IF(O13<=Assumptions!$B$31, Assumptions!$D$30 + (O13-Assumptions!$B$30)*Assumptions!$C$30, IF(O13<=Assumptions!$B$32, Assumptions!$D$31 + (O13-Assumptions!$B$31)*Assumptions!$C$31, IF(O13<=Assumptions!$B$33, Assumptions!$D$32 + (O13-Assumptions!$B$32)*Assumptions!$C$32, IF(O13<=Assumptions!$B$34, Assumptions!$D$33 + (O13-Assumptions!$B$33)*Assumptions!$C$33, IF(O13<=Assumptions!$B$35, Assumptions!$D$34 + (O13-Assumptions!$B$34)*Assumptions!$C$34, Assumptions!$D$35 + (O13-Assumptions!$B$35)*Assumptions!$C$35))))))) -> 8030.6367 | Q13: =L13 -> 185436.36 | R13: =IF('Capital Gains'!G13<=0, 0, MIN('Schedule A'!R13, L13)) -> 0 | S13: =MAX(0, N13 - I13) -> 0 | T13: =IF('Capital Gains'!G13<=0, 0, MAX(0, L13 - S13)) -> 185436.36 | U13: =IF(T13<=0, 0, IF((O13+T13)<=Assumptions!$B$46, 0, IF(O13>=Assumptions!$B$46, T13*Assumptions!$C$46, (O13+T13-Assumptions!$B$46)*Assumptions!$C$46))) -> 0 | V13: =IF(M13<=250000, 0, 0.038 * MIN(M13 - 250000, D13 + T13)) -> 7421.4825 | W13: =P13 + U13 + V13 -> 15452.119 | X13: =C13 + D13 + E13 + 'Capital Gains'!F13 -> 499425.55 | Y13: =IF(MAX(0, X13 - 20500)<=0, 0, IF(MAX(0, X13 - 20500)<=Assumptions!$B$20, MAX(0, X13 - 20500)*Assumptions!$C$19, IF(MAX(0, X13 - 20500)<=Assumptions!$B$21, Assumptions!$D$20 + (MAX(0, X13 - 20500)-Assumptions!$B$20)*Assumptions!$C$20, IF(MAX(0, X13 - 20500)<=Assumptions!$B$22, Assumptions!$D$21 + (MAX(0, X13 - 20500)-Assumptions!$B$21)*Assumptions!$C$21, IF(MAX(0, X13 - 20500)<=Assumptions!$B$23, Assumptions!$D$22 + (MAX(0, X13 - 20500)-Assumptions!$B$22)*Assumptions!$C$22, IF(MAX(0, X13 - 20500)<=Assumptions!$B$24, Assumptions!$D$23 + (MAX(0, X13 - 20500)-Assumptions!$B$23)*Assumptions!$C$23, IF(MAX(0, X13 - 20500)<=Assumptions!$B$25, Assumptions!$D$24 + (MAX(0, X13 - 20500)-Assumptions!$B$25)*Assumptions!$C$24, Assumptions!$D$25 + (MAX(0, X13 - 20500)-Assumptions!$B$25)*Assumptions!$C$25))))))) -> 26465.058 | Z13: =W13 + Y13 -> 41917.177 | AA13: =H13 + MIN(J13, 'Capital Gains'!F13) -> 0
A14: 2038 | B14: ='Outside Income'!D14 * 0.85 -> 47795.232 | C14: ='Outside Income'!E14 -> 96198.916 | D14: =IF('Capital Gains'!G14<=0, 0, 'Outside Income'!G14) -> 8195.9673 | E14: ='Inherited and Roth IRA'!K14 | F14: =IF('Capital Gains'!F14<=0, 0, MIN(MAX(0, 'Schedule A'!P14 - D14), 'Capital Gains'!F14)) -> 238727.87 | G14: =B14 + C14 + D14 + E14 + F14 -> 390917.99 | H14: 0 | I14: =MAX(0, G14 - H14) -> 390917.99 | J14: 0 | K14: =IF('Capital Gains'!G14<=0, 0, MAX(0, 'Capital Gains'!F14 - F14)) -> 191551.45 | L14: =IF('Capital Gains'!G14<=0, 0, MAX(0, K14 - J14)) -> 191551.45 | M14: =I14 + L14 -> 582469.44 | N14: ='Schedule A'!M14 -> 308231.63 | O14: =MAX(0, I14 - N14) -> 82686.356 | P14: =IF(O14<=0, 0, IF(O14<=Assumptions!$B$30, O14*Assumptions!$C$29, IF(O14<=Assumptions!$B$31, Assumptions!$D$30 + (O14-Assumptions!$B$30)*Assumptions!$C$30, IF(O14<=Assumptions!$B$32, Assumptions!$D$31 + (O14-Assumptions!$B$31)*Assumptions!$C$31, IF(O14<=Assumptions!$B$33, Assumptions!$D$32 + (O14-Assumptions!$B$32)*Assumptions!$C$32, IF(O14<=Assumptions!$B$34, Assumptions!$D$33 + (O14-Assumptions!$B$33)*Assumptions!$C$33, IF(O14<=Assumptions!$B$35, Assumptions!$D$34 + (O14-Assumptions!$B$34)*Assumptions!$C$34, Assumptions!$D$35 + (O14-Assumptions!$B$35)*Assumptions!$C$35))))))) -> 9458.3627 | Q14: =L14 -> 191551.45 | R14: =IF('Capital Gains'!G14<=0, 0, MIN('Schedule A'!R14, L14)) -> 0 | S14: =MAX(0, N14 - I14) -> 0 | T14: =IF('Capital Gains'!G14<=0, 0, MAX(0, L14 - S14)) -> 191551.45 | U14: =IF(T14<=0, 0, IF((O14+T14)<=Assumptions!$B$46, 0, IF(O14>=Assumptions!$B$46, T14*Assumptions!$C$46, (O14+T14-Assumptions!$B$46)*Assumptions!$C$46))) -> 0 | V14: =IF(M14<=250000, 0, 0.038 * MIN(M14 - 250000, D14 + T14)) -> 7590.4019 | W14: =P14 + U14 + V14 -> 17048.765 | X14: =C14 + D14 + E14 + 'Capital Gains'!F14 -> 534674.21 | Y14: =IF(MAX(0, X14 - 20500)<=0, 0, IF(MAX(0, X14 - 20500)<=Assumptions!$B$20, MAX(0, X14 - 20500)*Assumptions!$C$19, IF(MAX(0, X14 - 20500)<=Assumptions!$B$21, Assumptions!$D$20 + (MAX(0, X14 - 20500)-Assumptions!$B$20)*Assumptions!$C$20, IF(MAX(0, X14 - 20500)<=Assumptions!$B$22, Assumptions!$D$21 + (MAX(0, X14 - 20500)-Assumptions!$B$21)*Assumptions!$C$21, IF(MAX(0, X14 - 20500)<=Assumptions!$B$23, Assumptions!$D$22 + (MAX(0, X14 - 20500)-Assumptions!$B$22)*Assumptions!$C$22, IF(MAX(0, X14 - 20500)<=Assumptions!$B$24, Assumptions!$D$23 + (MAX(0, X14 - 20500)-Assumptions!$B$23)*Assumptions!$C$23, IF(MAX(0, X14 - 20500)<=Assumptions!$B$25, Assumptions!$D$24 + (MAX(0, X14 - 20500)-Assumptions!$B$25)*Assumptions!$C$24, Assumptions!$D$25 + (MAX(0, X14 - 20500)-Assumptions!$B$25)*Assumptions!$C$25))))))) -> 28710.397 | Z14: =W14 + Y14 -> 45759.162 | AA14: =H14 + MIN(J14, 'Capital Gains'!F14) -> 0
A15: 2039 | B15: ='Outside Income'!D15 * 0.85 -> 48273.184 | C15: ='Outside Income'!E15 -> 105818.81 | D15: =IF('Capital Gains'!G15<=0, 0, 'Outside Income'!G15) -> 6271.3744 | E15: ='Inherited and Roth IRA'!K15 | F15: =IF('Capital Gains'!F15<=0, 0, MIN(MAX(0, 'Schedule A'!P15 - D15), 'Capital Gains'!F15)) -> 262875.61 | G15: =B15 + C15 + D15 + E15 + F15 -> 423238.98 | H15: 0 | I15: =MAX(0, G15 - H15) -> 423238.98 | J15: 0 | K15: =IF('Capital Gains'!G15<=0, 0, MAX(0, 'Capital Gains'!F15 - F15)) -> 194547.24 | L15: =IF('Capital Gains'!G15<=0, 0, MAX(0, K15 - J15)) -> 194547.24 | M15: =I15 + L15 -> 617786.22 | N15: ='Schedule A'!M15 -> 327806.02 | O15: =MAX(0, I15 - N15) -> 95432.958 | P15: =IF(O15<=0, 0, IF(O15<=Assumptions!$B$30, O15*Assumptions!$C$29, IF(O15<=Assumptions!$B$31, Assumptions!$D$30 + (O15-Assumptions!$B$30)*Assumptions!$C$30, IF(O15<=Assumptions!$B$32, Assumptions!$D$31 + (O15-Assumptions!$B$31)*Assumptions!$C$31, IF(O15<=Assumptions!$B$33, Assumptions!$D$32 + (O15-Assumptions!$B$32)*Assumptions!$C$32, IF(O15<=Assumptions!$B$34, Assumptions!$D$33 + (O15-Assumptions!$B$33)*Assumptions!$C$33, IF(O15<=Assumptions!$B$35, Assumptions!$D$34 + (O15-Assumptions!$B$34)*Assumptions!$C$34, Assumptions!$D$35 + (O15-Assumptions!$B$35)*Assumptions!$C$35))))))) -> 11101.251 | Q15: =L15 -> 194547.24 | R15: =IF('Capital Gains'!G15<=0, 0, MIN('Schedule A'!R15, L15)) -> 0 | S15: =MAX(0, N15 - I15) -> 0 | T15: =IF('Capital Gains'!G15<=0, 0, MAX(0, L15 - S15)) -> 194547.24 | U15: =IF(T15<=0, 0, IF((O15+T15)<=Assumptions!$B$46, 0, IF(O15>=Assumptions!$B$46, T15*Assumptions!$C$46, (O15+T15-Assumptions!$B$46)*Assumptions!$C$46))) -> 0 | V15: =IF(M15<=250000, 0, 0.038 * MIN(M15 - 250000, D15 + T15)) -> 7631.1073 | W15: =P15 + U15 + V15 -> 18732.358 | X15: =C15 + D15 + E15 + 'Capital Gains'!F15 -> 569513.03 | Y15: =IF(MAX(0, X15 - 20500)<=0, 0, IF(MAX(0, X15 - 20500)<=Assumptions!$B$20, MAX(0, X15 - 20500)*Assumptions!$C$19, IF(MAX(0, X15 - 20500)<=Assumptions!$B$21, Assumptions!$D$20 + (MAX(0, X15 - 20500)-Assumptions!$B$20)*Assumptions!$C$20, IF(MAX(0, X15 - 20500)<=Assumptions!$B$22, Assumptions!$D$21 + (MAX(0, X15 - 20500)-Assumptions!$B$21)*Assumptions!$C$21, IF(MAX(0, X15 - 20500)<=Assumptions!$B$23, Assumptions!$D$22 + (MAX(0, X15 - 20500)-Assumptions!$B$22)*Assumptions!$C$22, IF(MAX(0, X15 - 20500)<=Assumptions!$B$24, Assumptions!$D$23 + (MAX(0, X15 - 20500)-Assumptions!$B$23)*Assumptions!$C$23, IF(MAX(0, X15 - 20500)<=Assumptions!$B$25, Assumptions!$D$24 + (MAX(0, X15 - 20500)-Assumptions!$B$25)*Assumptions!$C$24, Assumptions!$D$25 + (MAX(0, X15 - 20500)-Assumptions!$B$25)*Assumptions!$C$25))))))) -> 30929.63 | Z15: =W15 + Y15 -> 49661.988 | AA15: =H15 + MIN(J15, 'Capital Gains'!F15) -> 0
A16: 2040 | B16: ='Outside Income'!D16 * 0.85 -> 48755.916 | C16: ='Outside Income'!E16 -> 116400.69 | D16: =IF('Capital Gains'!G16<=0, 0, 'Outside Income'!G16) -> 4064.7509 | E16: ='Inherited and Roth IRA'!K16 | F16: =IF('Capital Gains'!F16<=0, 0, MIN(MAX(0, 'Schedule A'!P16 - D16), 'Capital Gains'!F16)) -> 289305.46 | G16: =B16 + C16 + D16 + E16 + F16 -> 458526.82 | H16: 0 | I16: =MAX(0, G16 - H16) -> 458526.82 | J16: 0 | K16: =IF('Capital Gains'!G16<=0, 0, MAX(0, 'Capital Gains'!F16 - F16)) -> 194219.37 | L16: =IF('Capital Gains'!G16<=0, 0, MAX(0, K16 - J16)) -> 194219.37 | M16: =I16 + L16 -> 652746.19 | N16: ='Schedule A'!M16 -> 349407.25 | O16: =MAX(0, I16 - N16) -> 109119.57 | P16: =IF(O16<=0, 0, IF(O16<=Assumptions!$B$30, O16*Assumptions!$C$29, IF(O16<=Assumptions!$B$31, Assumptions!$D$30 + (O16-Assumptions!$B$30)*Assumptions!$C$30, IF(O16<=Assumptions!$B$32, Assumptions!$D$31 + (O16-Assumptions!$B$31)*Assumptions!$C$31, IF(O16<=Assumptions!$B$33, Assumptions!$D$32 + (O16-Assumptions!$B$32)*Assumptions!$C$32, IF(O16<=Assumptions!$B$34, Assumptions!$D$33 + (O16-Assumptions!$B$33)*Assumptions!$C$33, IF(O16<=Assumptions!$B$35, Assumptions!$D$34 + (O16-Assumptions!$B$34)*Assumptions!$C$34, Assumptions!$D$35 + (O16-Assumptions!$B$35)*Assumptions!$C$35))))))) -> 14112.305 | Q16: =L16 -> 194219.37 | R16: =IF('Capital Gains'!G16<=0, 0, MIN('Schedule A'!R16, L16)) -> 0 | S16: =MAX(0, N16 - I16) -> 0 | T16: =IF('Capital Gains'!G16<=0, 0, MAX(0, L16 - S16)) -> 194219.37 | U16: =IF(T16<=0, 0, IF((O16+T16)<=Assumptions!$B$46, 0, IF(O16>=Assumptions!$B$46, T16*Assumptions!$C$46, (O16+T16-Assumptions!$B$46)*Assumptions!$C$46))) -> 0 | V16: =IF(M16<=250000, 0, 0.038 * MIN(M16 - 250000, D16 + T16)) -> 7534.7967 | W16: =P16 + U16 + V16 -> 21647.102 | X16: =C16 + D16 + E16 + 'Capital Gains'!F16 -> 603990.28 | Y16: =IF(MAX(0, X16 - 20500)<=0, 0, IF(MAX(0, X16 - 20500)<=Assumptions!$B$20, MAX(0, X16 - 20500)*Assumptions!$C$19, IF(MAX(0, X16 - 20500)<=Assumptions!$B$21, Assumptions!$D$20 + (MAX(0, X16 - 20500)-Assumptions!$B$20)*Assumptions!$C$20, IF(MAX(0, X16 - 20500)<=Assumptions!$B$22, Assumptions!$D$21 + (MAX(0, X16 - 20500)-Assumptions!$B$21)*Assumptions!$C$21, IF(MAX(0, X16 - 20500)<=Assumptions!$B$23, Assumptions!$D$22 + (MAX(0, X16 - 20500)-Assumptions!$B$22)*Assumptions!$C$22, IF(MAX(0, X16 - 20500)<=Assumptions!$B$24, Assumptions!$D$23 + (MAX(0, X16 - 20500)-Assumptions!$B$23)*Assumptions!$C$23, IF(MAX(0, X16 - 20500)<=Assumptions!$B$25, Assumptions!$D$24 + (MAX(0, X16 - 20500)-Assumptions!$B$25)*Assumptions!$C$24, Assumptions!$D$25 + (MAX(0, X16 - 20500)-Assumptions!$B$25)*Assumptions!$C$25))))))) -> 33125.831 | Z16: =W16 + Y16 -> 54772.932 | AA16: =H16 + MIN(J16, 'Capital Gains'!F16) -> 0
A17: 2041 | B17: ='Outside Income'!D17 * 0.85 -> 49243.475 | C17: ='Outside Income'!E17 -> 128040.76 | D17: =IF('Capital Gains'!G17<=0, 0, 'Outside Income'!G17) -> 1546.1239 | E17: ='Inherited and Roth IRA'!K17 | F17: =IF('Capital Gains'!F17<=0, 0, MIN(MAX(0, 'Schedule A'!P17 - D17), 'Capital Gains'!F17)) -> 287706.77 | G17: =B17 + C17 + D17 + E17 + F17 -> 466537.12 | H17: 0 | I17: =MAX(0, G17 - H17) -> 466537.12 | J17: 0 | K17: =IF('Capital Gains'!G17<=0, 0, MAX(0, 'Capital Gains'!F17 - F17)) -> 0 | L17: =IF('Capital Gains'!G17<=0, 0, MAX(0, K17 - J17)) -> 0 | M17: =I17 + L17 -> 466537.12 | N17: ='Schedule A'!M17 -> 359255.61 | O17: =MAX(0, I17 - N17) -> 107281.52 | P17: =IF(O17<=0, 0, IF(O17<=Assumptions!$B$30, O17*Assumptions!$C$29, IF(O17<=Assumptions!$B$31, Assumptions!$D$30 + (O17-Assumptions!$B$30)*Assumptions!$C$30, IF(O17<=Assumptions!$B$32, Assumptions!$D$31 + (O17-Assumptions!$B$31)*Assumptions!$C$31, IF(O17<=Assumptions!$B$33, Assumptions!$D$32 + (O17-Assumptions!$B$32)*Assumptions!$C$32, IF(O17<=Assumptions!$B$34, Assumptions!$D$33 + (O17-Assumptions!$B$33)*Assumptions!$C$33, IF(O17<=Assumptions!$B$35, Assumptions!$D$34 + (O17-Assumptions!$B$34)*Assumptions!$C$34, Assumptions!$D$35 + (O17-Assumptions!$B$35)*Assumptions!$C$35))))))) -> 13707.934 | Q17: =L17 -> 0 | R17: =IF('Capital Gains'!G17<=0, 0, MIN('Schedule A'!R17, L17)) -> 0 | S17: =MAX(0, N17 - I17) -> 0 | T17: =IF('Capital Gains'!G17<=0, 0, MAX(0, L17 - S17)) -> 0 | U17: =IF(T17<=0, 0, IF((O17+T17)<=Assumptions!$B$46, 0, IF(O17>=Assumptions!$B$46, T17*Assumptions!$C$46, (O17+T17-Assumptions!$B$46)*Assumptions!$C$46))) -> 0 | V17: =IF(M17<=250000, 0, 0.038 * MIN(M17 - 250000, D17 + T17)) -> 58.75271 | W17: =P17 + U17 + V17 -> 13766.686 | X17: =C17 + D17 + E17 + 'Capital Gains'!F17 -> 417293.65 | Y17: =IF(MAX(0, X17 - 20500)<=0, 0, IF(MAX(0, X17 - 20500)<=Assumptions!$B$20, MAX(0, X17 - 20500)*Assumptions!$C$19, IF(MAX(0, X17 - 20500)<=Assumptions!$B$21, Assumptions!$D$20 + (MAX(0, X17 - 20500)-Assumptions!$B$20)*Assumptions!$C$20, IF(MAX(0, X17 - 20500)<=Assumptions!$B$22, Assumptions!$D$21 + (MAX(0, X17 - 20500)-Assumptions!$B$21)*Assumptions!$C$21, IF(MAX(0, X17 - 20500)<=Assumptions!$B$23, Assumptions!$D$22 + (MAX(0, X17 - 20500)-Assumptions!$B$22)*Assumptions!$C$22, IF(MAX(0, X17 - 20500)<=Assumptions!$B$24, Assumptions!$D$23 + (MAX(0, X17 - 20500)-Assumptions!$B$23)*Assumptions!$C$23, IF(MAX(0, X17 - 20500)<=Assumptions!$B$25, Assumptions!$D$24 + (MAX(0, X17 - 20500)-Assumptions!$B$25)*Assumptions!$C$24, Assumptions!$D$25 + (MAX(0, X17 - 20500)-Assumptions!$B$25)*Assumptions!$C$25))))))) -> 21233.255 | Z17: =W17 + Y17 -> 34999.942 | AA17: =H17 + MIN(J17, 'Capital Gains'!F17) -> 0
A18: 2042 | B18: ='Outside Income'!D18 * 0.85 -> 49735.91 | C18: ='Outside Income'!E18 -> 140844.83 | D18: =IF('Capital Gains'!G18<=0, 0, 'Outside Income'!G18) -> 0 | E18: ='Inherited and Roth IRA'!K18 | F18: =IF('Capital Gains'!F18<=0, 0, MIN(MAX(0, 'Schedule A'!P18 - D18), 'Capital Gains'!F18)) -> 0 | G18: =B18 + C18 + D18 + E18 + F18 -> 190580.74 | H18: 0 | I18: =MAX(0, G18 - H18) -> 190580.74 | J18: 0 | K18: =IF('Capital Gains'!G18<=0, 0, MAX(0, 'Capital Gains'!F18 - F18)) -> 0 | L18: =IF('Capital Gains'!G18<=0, 0, MAX(0, K18 - J18)) -> 0 | M18: =I18 + L18 -> 190580.74 | N18: ='Schedule A'!M18 -> 90699.444 | O18: =MAX(0, I18 - N18) -> 99881.298 | P18: =IF(O18<=0, 0, IF(O18<=Assumptions!$B$30, O18*Assumptions!$C$29, IF(O18<=Assumptions!$B$31, Assumptions!$D$30 + (O18-Assumptions!$B$30)*Assumptions!$C$30, IF(O18<=Assumptions!$B$32, Assumptions!$D$31 + (O18-Assumptions!$B$31)*Assumptions!$C$31, IF(O18<=Assumptions!$B$33, Assumptions!$D$32 + (O18-Assumptions!$B$32)*Assumptions!$C$32, IF(O18<=Assumptions!$B$34, Assumptions!$D$33 + (O18-Assumptions!$B$33)*Assumptions!$C$33, IF(O18<=Assumptions!$B$35, Assumptions!$D$34 + (O18-Assumptions!$B$34)*Assumptions!$C$34, Assumptions!$D$35 + (O18-Assumptions!$B$35)*Assumptions!$C$35))))))) -> 12079.886 | Q18: =L18 -> 0 | R18: =IF('Capital Gains'!G18<=0, 0, MIN('Schedule A'!R18, L18)) -> 0 | S18: =MAX(0, N18 - I18) -> 0 | T18: =IF('Capital Gains'!G18<=0, 0, MAX(0, L18 - S18)) -> 0 | U18: =IF(T18<=0, 0, IF((O18+T18)<=Assumptions!$B$46, 0, IF(O18>=Assumptions!$B$46, T18*Assumptions!$C$46, (O18+T18-Assumptions!$B$46)*Assumptions!$C$46))) -> 0 | V18: =IF(M18<=250000, 0, 0.038 * MIN(M18 - 250000, D18 + T18)) -> 0 | W18: =P18 + U18 + V18 -> 12079.886 | X18: =C18 + D18 + E18 + 'Capital Gains'!F18 -> 140844.83 | Y18: =IF(MAX(0, X18 - 20500)<=0, 0, IF(MAX(0, X18 - 20500)<=Assumptions!$B$20, MAX(0, X18 - 20500)*Assumptions!$C$19, IF(MAX(0, X18 - 20500)<=Assumptions!$B$21, Assumptions!$D$20 + (MAX(0, X18 - 20500)-Assumptions!$B$20)*Assumptions!$C$20, IF(MAX(0, X18 - 20500)<=Assumptions!$B$22, Assumptions!$D$21 + (MAX(0, X18 - 20500)-Assumptions!$B$21)*Assumptions!$C$21, IF(MAX(0, X18 - 20500)<=Assumptions!$B$23, Assumptions!$D$22 + (MAX(0, X18 - 20500)-Assumptions!$B$22)*Assumptions!$C$22, IF(MAX(0, X18 - 20500)<=Assumptions!$B$24, Assumptions!$D$23 + (MAX(0, X18 - 20500)-Assumptions!$B$23)*Assumptions!$C$23, IF(MAX(0, X18 - 20500)<=Assumptions!$B$25, Assumptions!$D$24 + (MAX(0, X18 - 20500)-Assumptions!$B$25)*Assumptions!$C$24, Assumptions!$D$25 + (MAX(0, X18 - 20500)-Assumptions!$B$25)*Assumptions!$C$25))))))) -> 5.0692498 | Z18: =W18 + Y18 -> 12084.955 | AA18: =H18 + MIN(J18, 'Capital Gains'!F18) -> 0
A19: 2043 | B19: ='Outside Income'!D19 * 0.85 -> 50233.269 | C19: ='Outside Income'!E19 -> 154929.32 | D19: =IF('Capital Gains'!G19<=0, 0, 'Outside Income'!G19) -> 0 | E19: ='Inherited and Roth IRA'!K19 | F19: =IF('Capital Gains'!F19<=0, 0, MIN(MAX(0, 'Schedule A'!P19 - D19), 'Capital Gains'!F19)) -> 0 | G19: =B19 + C19 + D19 + E19 + F19 -> 205162.59 | H19: 0 | I19: =MAX(0, G19 - H19) -> 205162.59 | J19: 0 | K19: =IF('Capital Gains'!G19<=0, 0, MAX(0, 'Capital Gains'!F19 - F19)) -> 0 | L19: =IF('Capital Gains'!G19<=0, 0, MAX(0, K19 - J19)) -> 0 | M19: =I19 + L19 -> 205162.59 | N19: ='Schedule A'!M19 -> 89605.806 | O19: =MAX(0, I19 - N19) -> 115556.78 | P19: =IF(O19<=0, 0, IF(O19<=Assumptions!$B$30, O19*Assumptions!$C$29, IF(O19<=Assumptions!$B$31, Assumptions!$D$30 + (O19-Assumptions!$B$30)*Assumptions!$C$30, IF(O19<=Assumptions!$B$32, Assumptions!$D$31 + (O19-Assumptions!$B$31)*Assumptions!$C$31, IF(O19<=Assumptions!$B$33, Assumptions!$D$32 + (O19-Assumptions!$B$32)*Assumptions!$C$32, IF(O19<=Assumptions!$B$34, Assumptions!$D$33 + (O19-Assumptions!$B$33)*Assumptions!$C$33, IF(O19<=Assumptions!$B$35, Assumptions!$D$34 + (O19-Assumptions!$B$34)*Assumptions!$C$34, Assumptions!$D$35 + (O19-Assumptions!$B$35)*Assumptions!$C$35))))))) -> 15528.491 | Q19: =L19 -> 0 | R19: =IF('Capital Gains'!G19<=0, 0, MIN('Schedule A'!R19, L19)) -> 0 | S19: =MAX(0, N19 - I19) -> 0 | T19: =IF('Capital Gains'!G19<=0, 0, MAX(0, L19 - S19)) -> 0 | U19: =IF(T19<=0, 0, IF((O19+T19)<=Assumptions!$B$46, 0, IF(O19>=Assumptions!$B$46, T19*Assumptions!$C$46, (O19+T19-Assumptions!$B$46)*Assumptions!$C$46))) -> 0 | V19: =IF(M19<=250000, 0, 0.038 * MIN(M19 - 250000, D19 + T19)) -> 0 | W19: =P19 + U19 + V19 -> 15528.491 | X19: =C19 + D19 + E19 + 'Capital Gains'!F19 -> 154929.32 | Y19: =IF(MAX(0, X19 - 20500)<=0, 0, IF(MAX(0, X19 - 20500)<=Assumptions!$B$20, MAX(0, X19 - 20500)*Assumptions!$C$19, IF(MAX(0, X19 - 20500)<=Assumptions!$B$21, Assumptions!$D$20 + (MAX(0, X19 - 20500)-Assumptions!$B$20)*Assumptions!$C$20, IF(MAX(0, X19 - 20500)<=Assumptions!$B$22, Assumptions!$D$21 + (MAX(0, X19 - 20500)-Assumptions!$B$21)*Assumptions!$C$21, IF(MAX(0, X19 - 20500)<=Assumptions!$B$23, Assumptions!$D$22 + (MAX(0, X19 - 20500)-Assumptions!$B$22)*Assumptions!$C$22, IF(MAX(0, X19 - 20500)<=Assumptions!$B$24, Assumptions!$D$23 + (MAX(0, X19 - 20500)-Assumptions!$B$23)*Assumptions!$C$23, IF(MAX(0, X19 - 20500)<=Assumptions!$B$25, Assumptions!$D$24 + (MAX(0, X19 - 20500)-Assumptions!$B$25)*Assumptions!$C$24, Assumptions!$D$25 + (MAX(0, X19 - 20500)-Assumptions!$B$25)*Assumptions!$C$25))))))) -> 783.94117 | Z19: =W19 + Y19 -> 16312.433 | AA19: =H19 + MIN(J19, 'Capital Gains'!F19) -> 0
A20: 2044 | B20: ='Outside Income'!D20 * 0.85 -> 50735.602 | C20: ='Outside Income'!E20 -> 85211.124 | D20: =IF('Capital Gains'!G20<=0, 0, 'Outside Income'!G20) -> 0 | E20: ='Inherited and Roth IRA'!K20 | F20: =IF('Capital Gains'!F20<=0, 0, MIN(MAX(0, 'Schedule A'!P20 - D20), 'Capital Gains'!F20)) -> 0 | G20: =B20 + C20 + D20 + E20 + F20 -> 135946.73 | H20: 0 | I20: =MAX(0, G20 - H20) -> 135946.73 | J20: 0 | K20: =IF('Capital Gains'!G20<=0, 0, MAX(0, 'Capital Gains'!F20 - F20)) -> 0 | L20: =IF('Capital Gains'!G20<=0, 0, MAX(0, K20 - J20)) -> 0 | M20: =I20 + L20 -> 135946.73 | N20: ='Schedule A'!M20 -> 94796.996 | O20: =MAX(0, I20 - N20) -> 41149.73 | P20: =IF(O20<=0, 0, IF(O20<=Assumptions!$B$30, O20*Assumptions!$C$29, IF(O20<=Assumptions!$B$31, Assumptions!$D$30 + (O20-Assumptions!$B$30)*Assumptions!$C$30, IF(O20<=Assumptions!$B$32, Assumptions!$D$31 + (O20-Assumptions!$B$31)*Assumptions!$C$31, IF(O20<=Assumptions!$B$33, Assumptions!$D$32 + (O20-Assumptions!$B$32)*Assumptions!$C$32, IF(O20<=Assumptions!$B$34, Assumptions!$D$33 + (O20-Assumptions!$B$33)*Assumptions!$C$33, IF(O20<=Assumptions!$B$35, Assumptions!$D$34 + (O20-Assumptions!$B$34)*Assumptions!$C$34, Assumptions!$D$35 + (O20-Assumptions!$B$35)*Assumptions!$C$35))))))) -> 4473.9676 | Q20: =L20 -> 0 | R20: =IF('Capital Gains'!G20<=0, 0, MIN('Schedule A'!R20, L20)) -> 0 | S20: =MAX(0, N20 - I20) -> 0 | T20: =IF('Capital Gains'!G20<=0, 0, MAX(0, L20 - S20)) -> 0 | U20: =IF(T20<=0, 0, IF((O20+T20)<=Assumptions!$B$46, 0, IF(O20>=Assumptions!$B$46, T20*Assumptions!$C$46, (O20+T20-Assumptions!$B$46)*Assumptions!$C$46))) -> 0 | V20: =IF(M20<=250000, 0, 0.038 * MIN(M20 - 250000, D20 + T20)) -> 0 | W20: =P20 + U20 + V20 -> 4473.9676 | X20: =C20 + D20 + E20 + 'Capital Gains'!F20 -> 85211.124 | Y20: =IF(MAX(0, X20 - 20500)<=0, 0, IF(MAX(0, X20 - 20500)<=Assumptions!$B$20, MAX(0, X20 - 20500)*Assumptions!$C$19, IF(MAX(0, X20 - 20500)<=Assumptions!$B$21, Assumptions!$D$20 + (MAX(0, X20 - 20500)-Assumptions!$B$20)*Assumptions!$C$20, IF(MAX(0, X20 - 20500)<=Assumptions!$B$22, Assumptions!$D$21 + (MAX(0, X20 - 20500)-Assumptions!$B$21)*Assumptions!$C$21, IF(MAX(0, X20 - 20500)<=Assumptions!$B$23, Assumptions!$D$22 + (MAX(0, X20 - 20500)-Assumptions!$B$22)*Assumptions!$C$22, IF(MAX(0, X20 - 20500)<=Assumptions!$B$24, Assumptions!$D$23 + (MAX(0, X20 - 20500)-Assumptions!$B$23)*Assumptions!$C$23, IF(MAX(0, X20 - 20500)<=Assumptions!$B$25, Assumptions!$D$24 + (MAX(0, X20 - 20500)-Assumptions!$B$25)*Assumptions!$C$24, Assumptions!$D$25 + (MAX(0, X20 - 20500)-Assumptions!$B$25)*Assumptions!$C$25))))))) -> 1165.4225 | Z20: =W20 + Y20 -> 5639.3901 | AA20: =H20 + MIN(J20, 'Capital Gains'!F20) -> 0
... A31: 2055 | B31: ='Outside Income'!D31 * 0.85 -> 56604.105 | C31: ='Outside Income'!E31 -> 0 | D31: =IF('Capital Gains'!G31<=0, 0, 'Outside Income'!G31) -> 0 | E31: ='Inherited and Roth IRA'!K31 | F31: =IF('Capital Gains'!F31<=0, 0, MIN(MAX(0, 'Schedule A'!P31 - D31), 'Capital Gains'!F31)) -> 0 | G31: =B31 + C31 + D31 + E31 + F31 -> 56604.105 | H31: 0 | I31: =MAX(0, G31 - H31) -> 56604.105 | J31: 0 | K31: =IF('Capital Gains'!G31<=0, 0, MAX(0, 'Capital Gains'!F31 - F31)) -> 0 | L31: =IF('Capital Gains'!G31<=0, 0, MAX(0, K31 - J31)) -> 0 | M31: =I31 + L31 -> 56604.105 | N31: ='Schedule A'!M31 -> 100747.69 | O31: =MAX(0, I31 - N31) -> 0 | P31: =IF(O31<=0, 0, IF(O31<=Assumptions!$B$30, O31*Assumptions!$C$29, IF(O31<=Assumptions!$B$31, Assumptions!$D$30 + (O31-Assumptions!$B$30)*Assumptions!$C$30, IF(O31<=Assumptions!$B$32, Assumptions!$D$31 + (O31-Assumptions!$B$31)*Assumptions!$C$31, IF(O31<=Assumptions!$B$33, Assumptions!$D$32 + (O31-Assumptions!$B$32)*Assumptions!$C$32, IF(O31<=Assumptions!$B$34, Assumptions!$D$33 + (O31-Assumptions!$B$33)*Assumptions!$C$33, IF(O31<=Assumptions!$B$35, Assumptions!$D$34 + (O31-Assumptions!$B$34)*Assumptions!$C$34, Assumptions!$D$35 + (O31-Assumptions!$B$35)*Assumptions!$C$35))))))) -> 0 | Q31: =L31 -> 0 | R31: =IF('Capital Gains'!G31<=0, 0, MIN('Schedule A'!R31, L31)) -> 0 | S31: =MAX(0, N31 - I31) -> 44143.587 | T31: =IF('Capital Gains'!G31<=0, 0, MAX(0, L31 - S31)) -> 0 | U31: =IF(T31<=0, 0, IF((O31+T31)<=Assumptions!$B$46, 0, IF(O31>=Assumptions!$B$46, T31*Assumptions!$C$46, (O31+T31-Assumptions!$B$46)*Assumptions!$C$46))) -> 0 | V31: =IF(M31<=250000, 0, 0.038 * MIN(M31 - 250000, D31 + T31)) -> 0 | W31: =P31 + U31 + V31 -> 0 | X31: =C31 + D31 + E31 + 'Capital Gains'!F31 -> 0 | Y31: =IF(MAX(0, X31 - 20500)<=0, 0, IF(MAX(0, X31 - 20500)<=Assumptions!$B$20, MAX(0, X31 - 20500)*Assumptions!$C$19, IF(MAX(0, X31 - 20500)<=Assumptions!$B$21, Assumptions!$D$20 + (MAX(0, X31 - 20500)-Assumptions!$B$20)*Assumptions!$C$20, IF(MAX(0, X31 - 20500)<=Assumptions!$B$22, Assumptions!$D$21 + (MAX(0, X31 - 20500)-Assumptions!$B$21)*Assumptions!$C$21, IF(MAX(0, X31 - 20500)<=Assumptions!$B$23, Assumptions!$D$22 + (MAX(0, X31 - 20500)-Assumptions!$B$22)*Assumptions!$C$22, IF(MAX(0, X31 - 20500)<=Assumptions!$B$24, Assumptions!$D$23 + (MAX(0, X31 - 20500)-Assumptions!$B$23)*Assumptions!$C$23, IF(MAX(0, X31 - 20500)<=Assumptions!$B$25, Assumptions!$D$24 + (MAX(0, X31 - 20500)-Assumptions!$B$25)*Assumptions!$C$24, Assumptions!$D$25 + (MAX(0, X31 - 20500)-Assumptions!$B$25)*Assumptions!$C$25))))))) -> 0 | Z31: =W31 + Y31 -> 0 | AA31: =H31 + MIN(J31, 'Capital Gains'!F31) -> 0

Sheet Schedule A
A1: Year | B1: Adjusted Gross Income (AGI) | C1: Unreimbursed Medical Expenses | D1: 7.5% Medical AGI Floor | E1: Deductible Medical Expense | F1: SALT Taxes Paid | G1: OBBBA Base SALT Cap | H1: SALT MAGI Phase-Down Adjustment | I1: Phased-Down SALT Cap | J1: Allowed SALT Deduction | K1: Mortgage Interest | L1: Charitable Contributions | M1: Total Schedule A Itemized Deductions | N1: Investment Interest Expense from Viatar K-1 | O1: Prior Year Interest Carryforward | P1: Total Available Investment Interest | Q1: Allowed Investment Interest Deduction | R1: Ending Interest Carryforward | S1: Optimal § 163(d) Election
A2: 2026 | B2: =Taxes!M2 -> 399408.88 | C2: 56847 | D2: =B2 * 0.075 -> 29955.666 | E2: =MAX(0, C2 - D2) -> 26891.334 | F2: 60000 | G2: 40400 | H2: 0 | I2: =G2 - H2 -> 40400 | J2: =MIN(F2, I2) -> 40400 | K2: 3746 | L2: 4000 | M2: =E2 + J2 + K2 + L2 + Q2 -> 162827.33 | N2: 87790 | O2: 0 | P2: =N2 + O2 -> 87790 | Q2: =MIN(P2, Taxes!D2 + S2) -> 87790 | R2: =P2 - Q2 -> 0 | S2: =Taxes!F2 -> 38918
A3: 2027 | B3: =Taxes!M3 -> 187549.58 | C3: 56847 | D3: =B3 * 0.075 -> 14066.218 | E3: =MAX(0, C3 - D3) -> 42780.782 | F3: 60000 | G3: 40400 | H3: 0 | I3: =G3 - H3 -> 40400 | J3: =MIN(F3, I3) -> 40400 | K3: 3746 | L3: 4000 | M3: =E3 + J3 + K3 + L3 + Q3 -> 167549.58 | N3: =N2*1.09 -> 95691.1 | O3: =R2 -> 0 | P3: =N3 + O3 -> 95691.1 | Q3: =MIN(P3, Taxes!D3 + S3) -> 76622.796 | R3: =P3 - Q3 -> 19068.304 | S3: =Taxes!F3 -> 59573.491
A4: 2028 | B4: =Taxes!M4 -> 224464.93 | C4: 56847 | D4: =B4 * 0.075 -> 16834.87 | E4: =MAX(0, C4 - D4) -> 40012.13 | F4: 60000 | G4: 40400 | H4: 0 | I4: =G4 - H4 -> 40400 | J4: =MIN(F4, I4) -> 40400 | K4: 3746 | L4: 4000 | M4: =E4 + J4 + K4 + L4 + Q4 -> 204464.93 | N4: =N3*1.09 -> 104303.3 | O4: =R3 -> 19068.304 | P4: =N4 + O4 -> 123371.6 | Q4: =MIN(P4, Taxes!D4 + S4) -> 116306.8 | R4: =P4 - Q4 -> 7064.8026 | S4: =Taxes!F4 -> 99433.903
A5: 2029 | B5: =Taxes!M5 -> 262347.07 | C5: 56847 | D5: =B5 * 0.075 -> 19676.03 | E5: =MAX(0, C5 - D5) -> 37170.97 | F5: 60000 | G5: 40400 | H5: 0 | I5: =G5 - H5 -> 40400 | J5: =MIN(F5, I5) -> 40400 | K5: 3746 | L5: 4000 | M5: =E5 + J5 + K5 + L5 + Q5 -> 206072.37 | N5: =N4*1.09 -> 113690.6 | O5: =R4 -> 7064.8026 | P5: =N5 + O5 -> 120755.4 | Q5: =MIN(P5, Taxes!D5 + S5) -> 120755.4 | R5: =P5 - Q5 -> 0 | S5: =Taxes!F5 -> 104145.73
A6: 2030 | B6: =Taxes!M6 -> 298888.67 | C6: 56847 | D6: =B6 * 0.075 -> 22416.65 | E6: =MAX(0, C6 - D6) -> 34430.35 | F6: 60000 | G6: 40400 | H6: 0 | I6: =G6 - H6 -> 40400 | J6: =MIN(F6, I6) -> 40400 | K6: 3746 | L6: 4000 | M6: =E6 + J6 + K6 + L6 + Q6 -> 206499.1 | N6: =N5*1.09 -> 123922.75 | O6: =R5 -> 0 | P6: =N6 + O6 -> 123922.75 | Q6: =MIN(P6, Taxes!D6 + S6) -> 123922.75 | R6: =P6 - Q6 -> 0 | S6: =Taxes!F6 -> 107673.62
A7: 2031 | B7: =Taxes!M7 -> 333496.87 | C7: 56847 | D7: =B7 * 0.075 -> 25012.266 | E7: =MAX(0, C7 - D7) -> 31834.734 | F7: 60000 | G7: 40400 | H7: 0 | I7: =G7 - H7 -> 40400 | J7: =MIN(F7, I7) -> 40400 | K7: 3746 | L7: 4000 | M7: =E7 + J7 + K7 + L7 + Q7 -> 215056.53 | N7: =N6*1.09 -> 135075.8 | O7: =R6 -> 0 | P7: =N7 + O7 -> 135075.8 | Q7: =MIN(P7, Taxes!D7 + S7) -> 135075.8 | R7: =P7 - Q7 -> 0 | S7: =Taxes!F7 -> 119296.09
A8: 2032 | B8: =Taxes!M8 -> 358021.01 | C8: 56847 | D8: =B8 * 0.075 -> 26851.576 | E8: =MAX(0, C8 - D8) -> 29995.424 | F8: 60000 | G8: 40400 | H8: 0 | I8: =G8 - H8 -> 40400 | J8: =MIN(F8, I8) -> 40400 | K8: 3746 | L8: 4000 | M8: =E8 + J8 + K8 + L8 + Q8 -> 225374.04 | N8: =N7*1.09 -> 147232.62 | O8: =R7 -> 0 | P8: =N8 + O8 -> 147232.62 | Q8: =MIN(P8, Taxes!D8 + S8) -> 147232.62 | R8: =P8 - Q8 -> 0 | S8: =Taxes!F8 -> 132043.95
A9: 2033 | B9: =Taxes!M9 -> 398672.41 | C9: 56847 | D9: =B9 * 0.075 -> 29900.431 | E9: =MAX(0, C9 - D9) -> 26946.569 | F9: 60000 | G9: 40400 | H9: 0 | I9: =G9 - H9 -> 40400 | J9: =MIN(F9, I9) -> 40400 | K9: 3746 | L9: 4000 | M9: =E9 + J9 + K9 + L9 + Q9 -> 235576.12 | N9: =N8*1.09 -> 160483.55 | O9: =R8 -> 0 | P9: =N9 + O9 -> 160483.55 | Q9: =MIN(P9, Taxes!D9 + S9) -> 160483.55 | R9: =P9 - Q9 -> 0 | S9: =Taxes!F9 -> 146021.57
A10: 2034 | B10: =Taxes!M10 -> 436595.01 | C10: 56847 | D10: =B10 * 0.075 -> 32744.626 | E10: =MAX(0, C10 - D10) -> 24102.374 | F10: 60000 | G10: 40400 | H10: 0 | I10: =G10 - H10 -> 40400 | J10: =MIN(F10, I10) -> 40400 | K10: 3746 | L10: 4000 | M10: =E10 + J10 + K10 + L10 + Q10 -> 247175.45 | N10: =N9*1.09 -> 174927.07 | O10: =R9 -> 0 | P10: =N10 + O10 -> 174927.07 | Q10: =MIN(P10, Taxes!D10 + S10) -> 174927.07 | R10: =P10 - Q10 -> 0 | S10: =Taxes!F10 -> 161342.86
A11: 2035 | B11: =Taxes!M11 -> 473870.8 | C11: 56847 | D11: =B11 * 0.075 -> 35540.31 | E11: =MAX(0, C11 - D11) -> 21306.69 | F11: 60000 | G11: 40400 | H11: 0 | I11: =G11 - H11 -> 40400 | J11: =MIN(F11, I11) -> 40400 | K11: 3746 | L11: 4000 | M11: =E11 + J11 + K11 + L11 + Q11 -> 260123.2 | N11: =N10*1.09 -> 190670.51 | O11: =R10 -> 0 | P11: =N11 + O11 -> 190670.51 | Q11: =MIN(P11, Taxes!D11 + S11) -> 190670.51 | R11: =P11 - Q11 -> 0 | S11: =Taxes!F11 -> 178132.15
A12: 2036 | B12: =Taxes!M12 -> 510567.37 | C12: 56847 | D12: =B12 * 0.075 -> 38292.553 | E12: =MAX(0, C12 - D12) -> 18554.447 | F12: 60000 | G12: 40400 | H12: 0 | I12: =G12 - H12 -> 40400 | J12: =MIN(F12, I12) -> 40400 | K12: 3746 | L12: 4000 | M12: =E12 + J12 + K12 + L12 + Q12 -> 274531.3 | N12: =N11*1.09 -> 207830.86 | O12: =R11 -> 0 | P12: =N12 + O12 -> 207830.86 | Q12: =MIN(P12, Taxes!D12 + S12) -> 207830.86 | R12: =P12 - Q12 -> 0 | S12: =Taxes!F12 -> 196525.11
A13: 2037 | B13: =Taxes!M13 -> 546747.56 | C13: 56847 | D13: =B13 * 0.075 -> 41006.067 | E13: =MAX(0, C13 - D13) -> 15840.933 | F13: 60000 | G13: 40400 | H13: 0 | I13: =G13 - H13 -> 40400 | J13: =MIN(F13, I13) -> 40400 | K13: 3746 | L13: 4000 | M13: =E13 + J13 + K13 + L13 + Q13 -> 290522.57 | N13: =N12*1.09 -> 226535.63 | O13: =R12 -> 0 | P13: =N13 + O13 -> 226535.63 | Q13: =MIN(P13, Taxes!D13 + S13) -> 226535.63 | R13: =P13 - Q13 -> 0 | S13: =Taxes!F13 -> 216669.82
A14: 2038 | B14: =Taxes!M14 -> 582469.44 | C14: 56847 | D14: =B14 * 0.075 -> 43685.208 | E14: =MAX(0, C14 - D14) -> 13161.792 | F14: 60000 | G14: 40400 | H14: 0 | I14: =G14 - H14 -> 40400 | J14: =MIN(F14, I14) -> 40400 | K14: 3746 | L14: 4000 | M14: =E14 + J14 + K14 + L14 + Q14 -> 308231.63 | N14: =N13*1.09 -> 246923.84 | O14: =R13 -> 0 | P14: =N14 + O14 -> 246923.84 | Q14: =MIN(P14, Taxes!D14 + S14) -> 246923.84 | R14: =P14 - Q14 -> 0 | S14: =Taxes!F14 -> 238727.87
... A31: 2055 | B31: =Taxes!M31 -> 56604.105 | C31: 56847 | D31: =B31 * 0.075 -> 4245.3079 | E31: =MAX(0, C31 - D31) -> 52601.692 | F31: 60000 | G31: 40400 | H31: 0 | I31: =G31 - H31 -> 40400 | J31: =MIN(F31, I31) -> 40400 | K31: 3746 | L31: 4000 | M31: =E31 + J31 + K31 + L31 + Q31 -> 100747.69 | N31: =N30*1.09 -> 1068595.9 | O31: =R30 -> 8030995.2 | P31: =N31 + O31 -> 9099591.1 | Q31: =MIN(P31, Taxes!D31 + S31) -> 0 | R31: =P31 - Q31 -> 9099591.1 | S31: =Taxes!F31 -> 0

Sheet Outside Income
A1: Year | B1: Ilene's Age | C1: Equitrust Annuity (Roth) | D1: Combined Social Security (1% COLA) | E1: Inherited IRA Distribution | F1: Total Outside Income | G1: Dividend Income
A2: 2026 | B2: 65 | C2: 0 | D2: 32080 | E2: 28258 | F2: =C2 + D2 + E2 -> 60338 | G2: =7272+41600 -> 48872
A3: =A2+1 -> 2027 | B3: =B2+1 -> 66 | C3: 86000 | D3: 50400 | E3: ='Inherited and Roth IRA'!G3 -> 33717.133 | F3: =C3 + D3 + E3 -> 170117.13 | G3: ='Capital Gains'!G3*Assumptions!B$6 -> 17049.305
A4: =A3+1 -> 2028 | B4: =B3+1 -> 67 | C4: 86000 | D4: =D3*1.01 -> 50904 | E4: ='Inherited and Roth IRA'!G4 -> 37088.846 | F4: =C4 + D4 + E4 -> 173992.85 | G4: ='Capital Gains'!G4*Assumptions!B$6 -> 16872.898
A5: =A4+1 -> 2029 | B5: =B4+1 -> 68 | C5: 86000 | D5: =D4*1.01 -> 51413.04 | E5: ='Inherited and Roth IRA'!G5 -> 40797.731 | F5: =C5 + D5 + E5 -> 178210.77 | G5: ='Capital Gains'!G5*Assumptions!B$6 -> 16609.67
A6: =A5+1 -> 2030 | B6: =B5+1 -> 69 | C6: 86000 | D6: =D5*1.01 -> 51927.17 | E6: ='Inherited and Roth IRA'!G6 -> 44877.504 | F6: =C6 + D6 + E6 -> 182804.67 | G6: ='Capital Gains'!G6*Assumptions!B$6 -> 16249.129
A7: =A6+1 -> 2031 | B7: =B6+1 -> 70 | C7: 86000 | D7: =D6*1.01 -> 52446.442 | E7: ='Inherited and Roth IRA'!G7 -> 49365.255 | F7: =C7 + D7 + E7 -> 187811.7 | G7: ='Capital Gains'!G7*Assumptions!B$6 -> 15779.708
A8: =A7+1 -> 2032 | B8: =B7+1 -> 71 | C8: 86000 | D8: =D7*1.01 -> 52970.907 | E8: ='Inherited and Roth IRA'!G8 -> 54301.78 | F8: =C8 + D8 + E8 -> 193272.69 | G8: ='Capital Gains'!G8*Assumptions!B$6 -> 15188.669
A9: =A8+1 -> 2033 | B9: =B8+1 -> 72 | C9: 86000 | D9: =D8*1.01 -> 53500.616 | E9: ='Inherited and Roth IRA'!G9 -> 59731.958 | F9: =C9 + D9 + E9 -> 199232.57 | G9: ='Capital Gains'!G9*Assumptions!B$6 -> 14461.984
A10: =A9+1 -> 2034 | B10: =B9+1 -> 73 | C10: 86000 | D10: =D9*1.01 -> 54035.622 | E10: ='Inherited and Roth IRA'!G10 -> 65705.154 | F10: =C10 + D10 + E10 -> 205740.78 | G10: ='Capital Gains'!G10*Assumptions!B$6 -> 13584.213
A11: =A10+1 -> 2035 | B11: =B10+1 -> 74 | C11: 86000 | D11: =D10*1.01 -> 54575.978 | E11: ='Inherited and Roth IRA'!G11 -> 72275.669 | F11: =C11 + D11 + E11 -> 212851.65 | G11: ='Capital Gains'!G11*Assumptions!B$6 -> 12538.364
A12: =A11+1 -> 2036 | B12: =B11+1 -> 75 | C12: 86000 | D12: =D11*1.01 -> 55121.738 | E12: ='Inherited and Roth IRA'!G12 -> 79503.236 | F12: =C12 + D12 + E12 -> 220624.97 | G12: ='Capital Gains'!G12*Assumptions!B$6 -> 11305.749
A13: =A12+1 -> 2037 | B13: =B12+1 -> 76 | C13: 86000 | D13: =D12*1.01 -> 55672.955 | E13: ='Inherited and Roth IRA'!G13 -> 87453.56 | F13: =C13 + D13 + E13 -> 229126.52 | G13: ='Capital Gains'!G13*Assumptions!B$6 -> 9865.8146
A14: =A13+1 -> 2038 | B14: =B13+1 -> 77 | C14: 86000 | D14: =D13*1.01 -> 56229.685 | E14: ='Inherited and Roth IRA'!G14 -> 96198.916 | F14: =C14 + D14 + E14 -> 238428.6 | G14: ='Capital Gains'!G14*Assumptions!B$6 -> 8195.9673
A15: =A14+1 -> 2039 | B15: =B14+1 -> 78 | C15: 86000 | D15: =D14*1.01 -> 56791.982 | E15: ='Inherited and Roth IRA'!G15 -> 105818.81 | F15: =C15 + D15 + E15 -> 248610.79 | G15: ='Capital Gains'!G15*Assumptions!B$6 -> 6271.3744
... A31: =A30+1 -> 2055 | B31: =B30+1 -> 94 | C31: 86000 | D31: =D30*1.01 -> 66593.065 | E31: ='Inherited and Roth IRA'!G31 -> 0 | F31: =C31 + D31 + E31 -> 152593.06 | G31: ='Capital Gains'!G31*Assumptions!B$6 -> 0

Sheet Inherited and Roth IRA
A1: Year | B1: Ilene's Age | C1: IRS Divisor | D1: Inherited IRA Beginning Balance | E1: IRS Mandatory RMD | F1: Extra Withdrawal to Pay Taxes | G1: Total Gross Distribution | H1: Inherited IRA Ending Balance | J1: Traditional IRA | K1: Conversion to Roth IRA | L1: Election Cap | M1: Roth IRA Balance | N1: Roth IRA withdrawal to cover budget | O1: Ending Roth Balance
A2: 2026 | B2: 65 | C2: 18.5 | D2: =Assumptions!G3 -> 623766.96 | E2: =IF(D2<=0, 0, MIN(D2, D2/C2)) -> 33717.133 | F2: =MIN(D2 - E2, MAX(0, Assumptions!$B$28 - E2)) -> 0 | G2: =E2 + F2 -> 33717.133 | H2: =Assumptions!G3-G2 -> 590049.83 | J2: 1039869 | K2: 200000 | L2: =if(K2>0,0,999999) -> 0 | M2: =Assumptions!G4 -> 2133346.2 | N2: ='Cash Flow'!G2 -> 0 | O2: =M2-N2 -> 2133346.2
A3: =A2+1 -> 2027 | B3: =B2+1 -> 66 | C3: =IF(D3<=0, 0, MAX(1, C2-1)) -> 17.5 | D3: =H2 -> 590049.83 | E3: =IF(D3<=0, 0, MIN(D3, D3/C3)) -> 33717.133 | F3: =MIN(D3 - E3, MAX(0, Assumptions!$B$28 - E3)) -> 0 | G3: =E3 + F3 -> 33717.133 | H3: =MAX(0, (D3-G3)*(1+Assumptions!B$8)) -> 611965.97 | J3: =max(0,((J2-K2)*1.1)) -> 923855.9 | K3: =K2 -> 200000 | L3: =if(K3>0,0,999999) -> 0 | M3: =(O2*1.1) -> 2346680.8 | N3: ='Cash Flow'!G3 -> 0 | O3: =M3-N3 -> 2346680.8
A4: =A3+1 -> 2028 | B4: =B3+1 -> 67 | C4: =IF(D4<=0, 0, MAX(1, C3-1)) -> 16.5 | D4: =H3 -> 611965.97 | E4: =IF(D4<=0, 0, MIN(D4, D4/C4)) -> 37088.846 | F4: =MIN(D4 - E4, MAX(0, Assumptions!$B$28 - E4)) -> 0 | G4: =E4 + F4 -> 37088.846 | H4: =MAX(0, (D4-G4)*(1+Assumptions!B$8)) -> 632364.83 | J4: =max(0,((J3-K3)*1.1)) -> 796241.49 | K4: =K3 -> 200000 | L4: =if(K4>0,0,999999) -> 0 | M4: =(O3*1.1) -> 2581348.9 | N4: ='Cash Flow'!G4 -> 0 | O4: =M4-N4 -> 2581348.9
A5: =A4+1 -> 2029 | B5: =B4+1 -> 68 | C5: =IF(D5<=0, 0, MAX(1, C4-1)) -> 15.5 | D5: =H4 -> 632364.83 | E5: =IF(D5<=0, 0, MIN(D5, D5/C5)) -> 40797.731 | F5: =MIN(D5 - E5, MAX(0, Assumptions!$B$28 - E5)) -> 0 | G5: =E5 + F5 -> 40797.731 | H5: =MAX(0, (D5-G5)*(1+Assumptions!B$8)) -> 650723.81 | J5: =max(0,((J4-K4)*1.1)) -> 655865.64 | K5: =K4 -> 200000 | L5: =if(K5>0,0,999999) -> 0 | M5: =(O4*1.1) -> 2839483.8 | N5: ='Cash Flow'!G5 -> 0 | O5: =M5-N5 -> 2839483.8
A6: =A5+1 -> 2030 | B6: =B5+1 -> 69 | C6: =IF(D6<=0, 0, MAX(1, C5-1)) -> 14.5 | D6: =H5 -> 650723.81 | E6: =IF(D6<=0, 0, MIN(D6, D6/C6)) -> 44877.504 | F6: =MIN(D6 - E6, MAX(0, Assumptions!$B$28 - E6)) -> 0 | G6: =E6 + F6 -> 44877.504 | H6: =MAX(0, (D6-G6)*(1+Assumptions!B$8)) -> 666430.94 | J6: =max(0,((J5-K5)*1.1)) -> 501452.2 | K6: =K5 -> 200000 | L6: =if(K6>0,0,999999) -> 0 | M6: =(O5*1.1) -> 3123432.2 | N6: ='Cash Flow'!G6 -> 0 | O6: =M6-N6 -> 3123432.2
A7: =A6+1 -> 2031 | B7: =B6+1 -> 70 | C7: =IF(D7<=0, 0, MAX(1, C6-1)) -> 13.5 | D7: =H6 -> 666430.94 | E7: =IF(D7<=0, 0, MIN(D7, D7/C7)) -> 49365.255 | F7: =MIN(D7 - E7, MAX(0, Assumptions!$B$28 - E7)) -> 0 | G7: =E7 + F7 -> 49365.255 | H7: =MAX(0, (D7-G7)*(1+Assumptions!B$8)) -> 678772.25 | J7: =max(0,((J6-K6)*1.1)) -> 331597.42 | K7: =K6 -> 200000 | L7: =if(K7>0,0,999999) -> 0 | M7: =(O6*1.1) -> 3435775.4 | N7: ='Cash Flow'!G7 -> 0 | O7: =M7-N7 -> 3435775.4
A8: =A7+1 -> 2032 | B8: =B7+1 -> 71 | C8: =IF(D8<=0, 0, MAX(1, C7-1)) -> 12.5 | D8: =H7 -> 678772.25 | E8: =IF(D8<=0, 0, MIN(D8, D8/C8)) -> 54301.78 | F8: =MIN(D8 - E8, MAX(0, Assumptions!$B$28 - E8)) -> 0 | G8: =E8 + F8 -> 54301.78 | H8: =MAX(0, (D8-G8)*(1+Assumptions!B$8)) -> 686917.52 | J8: =max(0,((J7-K7)*1.1)) -> 144757.17 | K8: =J8 -> 144757.17 | L8: =if(K8>0,0,999999) -> 0 | M8: =(O7*1.1) -> 3779353 | N8: ='Cash Flow'!G8 -> 0 | O8: =M8-N8 -> 3779353
A9: =A8+1 -> 2033 | B9: =B8+1 -> 72 | C9: =IF(D9<=0, 0, MAX(1, C8-1)) -> 11.5 | D9: =H8 -> 686917.52 | E9: =IF(D9<=0, 0, MIN(D9, D9/C9)) -> 59731.958 | F9: =MIN(D9 - E9, MAX(0, Assumptions!$B$28 - E9)) -> 0 | G9: =E9 + F9 -> 59731.958 | H9: =MAX(0, (D9-G9)*(1+Assumptions!B$8)) -> 689904.12 | J9: =max(0,((J8-K8)*1.1)) -> 0 | K9: 0 | L9: =if(K9>0,0,999999) -> 999999 | M9: =(O8*1.1) -> 4157288.3 | N9: ='Cash Flow'!G9 -> 0 | O9: =M9-N9 -> 4157288.3
A10: =A9+1 -> 2034 | B10: =B9+1 -> 73 | C10: =IF(D10<=0, 0, MAX(1, C9-1)) -> 10.5 | D10: =H9 -> 689904.12 | E10: =IF(D10<=0, 0, MIN(D10, D10/C10)) -> 65705.154 | F10: =MIN(D10 - E10, MAX(0, Assumptions!$B$28 - E10)) -> 0 | G10: =E10 + F10 -> 65705.154 | H10: =MAX(0, (D10-G10)*(1+Assumptions!B$8)) -> 686618.86 | J10: =max(0,((J9-K9)*1.1)) -> 0 | K10: =K9 -> 0 | L10: =if(K10>0,0,999999) -> 999999 | M10: =(O9*1.1) -> 4573017.1 | N10: ='Cash Flow'!G10 -> 0 | O10: =M10-N10 -> 4573017.1
A11: =A10+1 -> 2035 | B11: =B10+1 -> 74 | C11: =IF(D11<=0, 0, MAX(1, C10-1)) -> 9.5 | D11: =H10 -> 686618.86 | E11: =IF(D11<=0, 0, MIN(D11, D11/C11)) -> 72275.669 | F11: =MIN(D11 - E11, MAX(0, Assumptions!$B$28 - E11)) -> 0 | G11: =E11 + F11 -> 72275.669 | H11: =MAX(0, (D11-G11)*(1+Assumptions!B$8)) -> 675777.51 | J11: =max(0,((J10-K10)*1.1)) -> 0 | K11: =K10 -> 0 | L11: =if(K11>0,0,999999) -> 999999 | M11: =(O10*1.1) -> 5030318.8 | N11: ='Cash Flow'!G11 -> 0 | O11: =M11-N11 -> 5030318.8
A12: =A11+1 -> 2036 | B12: =B11+1 -> 75 | C12: =IF(D12<=0, 0, MAX(1, C11-1)) -> 8.5 | D12: =H11 -> 675777.51 | E12: =IF(D12<=0, 0, MIN(D12, D12/C12)) -> 79503.236 | F12: =MIN(D12 - E12, MAX(0, Assumptions!$B$28 - E12)) -> 0 | G12: =E12 + F12 -> 79503.236 | H12: =MAX(0, (D12-G12)*(1+Assumptions!B$8)) -> 655901.7 | L12: =if(K12>0,0,999999) -> 999999 | M12: =(O11*1.1) -> 5533350.7 | N12: ='Cash Flow'!G12 -> 0 | O12: =M12-N12 -> 5533350.7
A13: =A12+1 -> 2037 | B13: =B12+1 -> 76 | C13: =IF(D13<=0, 0, MAX(1, C12-1)) -> 7.5 | D13: =H12 -> 655901.7 | E13: =IF(D13<=0, 0, MIN(D13, D13/C13)) -> 87453.56 | F13: =MIN(D13 - E13, MAX(0, Assumptions!$B$28 - E13)) -> 0 | G13: =E13 + F13 -> 87453.56 | H13: =MAX(0, (D13-G13)*(1+Assumptions!B$8)) -> 625292.95 | L13: =if(K13>0,0,999999) -> 999999 | M13: =(O12*1.1) -> 6086685.8 | N13: ='Cash Flow'!G13 -> 0 | O13: =M13-N13 -> 6086685.8
A14: =A13+1 -> 2038 | B14: =B13+1 -> 77 | C14: =IF(D14<=0, 0, MAX(1, C13-1)) -> 6.5 | D14: =H13 -> 625292.95 | E14: =IF(D14<=0, 0, MIN(D14, D14/C14)) -> 96198.916 | F14: =MIN(D14 - E14, MAX(0, Assumptions!$B$28 - E14)) -> 0 | G14: =E14 + F14 -> 96198.916 | H14: =MAX(0, (D14-G14)*(1+Assumptions!B$8)) -> 582003.44 | L14: =if(K14>0,0,999999) -> 999999 | M14: =(O13*1.1) -> 6695354.3 | N14: ='Cash Flow'!G14 -> 0 | O14: =M14-N14 -> 6695354.3
A15: =A14+1 -> 2039 | B15: =B14+1 -> 78 | C15: =IF(D15<=0, 0, MAX(1, C14-1)) -> 5.5 | D15: =H14 -> 582003.44 | E15: =IF(D15<=0, 0, MIN(D15, D15/C15)) -> 105818.81 | F15: =MIN(D15 - E15, MAX(0, Assumptions!$B$28 - E15)) -> 0 | G15: =E15 + F15 -> 105818.81 | H15: =MAX(0, (D15-G15)*(1+Assumptions!B$8)) -> 523803.1 | L15: =if(K15>0,0,999999) -> 999999 | M15: =(O14*1.1) -> 7364889.8 | N15: ='Cash Flow'!G15 -> 0 | O15: =M15-N15 -> 7364889.8
A16: =A15+1 -> 2040 | B16: =B15+1 -> 79 | C16: =IF(D16<=0, 0, MAX(1, C15-1)) -> 4.5 | D16: =H15 -> 523803.1 | E16: =IF(D16<=0, 0, MIN(D16, D16/C16)) -> 116400.69 | F16: =MIN(D16 - E16, MAX(0, Assumptions!$B$28 - E16)) -> 0 | G16: =E16 + F16 -> 116400.69 | H16: =MAX(0, (D16-G16)*(1+Assumptions!B$8)) -> 448142.65 | L16: =if(K16>0,0,999999) -> 999999 | M16: =(O15*1.1) -> 8101378.7 | N16: ='Cash Flow'!G16 -> 0 | O16: =M16-N16 -> 8101378.7
A17: =A16+1 -> 2041 | B17: =B16+1 -> 80 | C17: =IF(D17<=0, 0, MAX(1, C16-1)) -> 3.5 | D17: =H16 -> 448142.65 | E17: =IF(D17<=0, 0, MIN(D17, D17/C17)) -> 128040.76 | F17: =MIN(D17 - E17, MAX(0, Assumptions!$B$28 - E17)) -> 0 | G17: =E17 + F17 -> 128040.76 | H17: =MAX(0, (D17-G17)*(1+Assumptions!B$8)) -> 352112.08 | L17: =if(K17>0,0,999999) -> 999999 | M17: =(O16*1.1) -> 8911516.6 | N17: ='Cash Flow'!G17 -> 276015.87 | O17: =M17-N17 -> 8635500.7
A18: =A17+1 -> 2042 | B18: =B17+1 -> 81 | C18: =IF(D18<=0, 0, MAX(1, C17-1)) -> 2.5 | D18: =H17 -> 352112.08 | E18: =IF(D18<=0, 0, MIN(D18, D18/C18)) -> 140844.83 | F18: =MIN(D18 - E18, MAX(0, Assumptions!$B$28 - E18)) -> 0 | G18: =E18 + F18 -> 140844.83 | H18: =MAX(0, (D18-G18)*(1+Assumptions!B$8)) -> 232393.97 | L18: =if(K18>0,0,999999) -> 999999 | M18: =(O17*1.1) -> 9499050.8 | N18: ='Cash Flow'!G18 -> 649422.78 | O18: =M18-N18 -> 8849628
A19: =A18+1 -> 2043 | B19: =B18+1 -> 82 | C19: =IF(D19<=0, 0, MAX(1, C18-1)) -> 1.5 | D19: =H18 -> 232393.97 | E19: =IF(D19<=0, 0, MIN(D19, D19/C19)) -> 154929.32 | F19: =MIN(D19 - E19, MAX(0, Assumptions!$B$28 - E19)) -> 0 | G19: =E19 + F19 -> 154929.32 | H19: =MAX(0, (D19-G19)*(1+Assumptions!B$8)) -> 85211.124 | L19: =if(K19>0,0,999999) -> 999999 | M19: =(O18*1.1) -> 9734590.8 | N19: ='Cash Flow'!G19 -> 662796.58 | O19: =M19-N19 -> 9071794.3
A20: =A19+1 -> 2044 | B20: =B19+1 -> 83 | C20: =IF(D20<=0, 0, MAX(1, C19-1)) -> 1 | D20: =H19 -> 85211.124 | E20: =IF(D20<=0, 0, MIN(D20, D20/C20)) -> 85211.124 | F20: =MIN(D20 - E20, MAX(0, Assumptions!$B$28 - E20)) -> 0 | G20: =E20 + F20 -> 85211.124 | H20: =MAX(0, (D20-G20)*(1+Assumptions!B$8)) -> 0 | L20: =if(K20>0,0,999999) -> 999999 | M20: =(O19*1.1) -> 9978973.7 | N20: ='Cash Flow'!G20 -> 760808.51 | O20: =M20-N20 -> 9218165.2
A21: =A20+1 -> 2045 | B21: =B20+1 -> 84 | C21: =IF(D21<=0, 0, MAX(1, C20-1)) -> 0 | D21: =H20 -> 0 | E21: =IF(D21<=0, 0, MIN(D21, D21/C21)) -> 0 | F21: =MIN(D21 - E21, MAX(0, Assumptions!$B$28 - E21)) -> 0 | G21: =E21 + F21 -> 0 | H21: =MAX(0, (D21-G21)*(1+Assumptions!B$8)) -> 0 | L21: =if(K21>0,0,999999) -> 999999 | M21: =(O20*1.1) -> 10139982 | N21: ='Cash Flow'!G21 -> 875174 | O21: =M21-N21 -> 9264807.7
A22: =A21+1 -> 2046 | B22: =B21+1 -> 85 | C22: =IF(D22<=0, 0, MAX(1, C21-1)) -> 0 | D22: =H21 -> 0 | E22: =IF(D22<=0, 0, MIN(D22, D22/C22)) -> 0 | F22: =MIN(D22 - E22, MAX(0, Assumptions!$B$28 - E22)) -> 0 | G22: =E22 + F22 -> 0 | H22: =MAX(0, (D22-G22)*(1+Assumptions!B$8)) -> 0 | L22: =if(K22>0,0,999999) -> 999999 | M22: =(O21*1.1) -> 10191288 | N22: ='Cash Flow'!G22 -> 905214.94 | O22: =M22-N22 -> 9286073.5
A23: =A22+1 -> 2047 | B23: =B22+1 -> 86 | C23: =IF(D23<=0, 0, MAX(1, C22-1)) -> 0 | D23: =H22 -> 0 | E23: =IF(D23<=0, 0, MIN(D23, D23/C23)) -> 0 | F23: =MIN(D23 - E23, MAX(0, Assumptions!$B$28 - E23)) -> 0 | G23: =E23 + F23 -> 0 | H23: =MAX(0, (D23-G23)*(1+Assumptions!B$8)) -> 0 | L23: =if(K23>0,0,999999) -> 999999 | M23: =(O22*1.1) -> 10214681 | N23: ='Cash Flow'!G23 -> 936169.16 | O23: =M23-N23 -> 9278511.7
... A31: =A30+1 -> 2055 | B31: =B30+1 -> 94 | C31: =IF(D31<=0, 0, MAX(1, C30-1)) -> 0 | D31: =H30 -> 0 | E31: =IF(D31<=0, 0, MIN(D31, D31/C31)) -> 0 | F31: =MIN(D31 - E31, MAX(0, Assumptions!$B$28 - E31)) -> 0 | G31: =E31 + F31 -> 0 | H31: =MAX(0, (D31-G31)*(1+Assumptions!B$8)) -> 0 | L31: =if(K31>0,0,999999) -> 999999 | M31: =(O30*1.1) -> 8843807.3 | N31: ='Cash Flow'!G31 -> 1220163.5 | O31: =M31-N31 -> 7623643.7

Sheet Capital Gains
A1: Year | B1: VUG Share Price | C1: Portfolio Withdrawal Needed | D1: Actual VUG Dollars Sold | E1: VUG Shares Sold | F1: Realized Capital Gains | G1: Taxable Pool Start of Year | H1: Taxable Pool After Shares Sold at Beginning of Year | I1: Taxable Pool End of Year
A2: 2026 | B2: =Assumptions!D$2* ((1+Assumptions!B$5*0.416666)) -> 93.40295 | C2: 0 | D2: =MAX(0, MIN(G2, C2)) -> 0 | E2: =IF(B2>0, D2/B2, 0) -> 0 | F2: =926393-556210-56667 -> 313516 | G2: =Assumptions!G2 -> 3964954.7 | H2: =MAX(0, G2 - D2) -> 3964954.7 | I2: =Assumptions!G2 -> 3964954.7
A3: =A2+1 -> 2027 | B3: =B2*(1+Assumptions!B$5) -> 103.67727 | C3: =MAX(0, MIN(G3, Main!D3)) -> 429882.87 | D3: =MAX(0, MIN(G3, C3)) -> 429882.87 | E3: =IF(B3>0, D3/B3, 0) -> 4146.3558 | F3: =IF(G3>0, E3 * (B3 - Assumptions!D$2), 0) -> 59573.491 | G3: =IF(I2>0, I2, 0) -> 3964954.7 | H3: =MAX(0, G3 - D3) -> 3535071.8 | I3: =IF(G3>0, MAX(0, H3 * (1 + Assumptions!B$5)), 0) -> 3923929.7
A4: =A3+1 -> 2028 | B4: =B3*(1+Assumptions!B$5) -> 115.08177 | C4: =MAX(0, MIN(G4, Main!D4)) -> 444007.15 | D4: =MAX(0, MIN(G4, C4)) -> 444007.15 | E4: =IF(B4>0, D4/B4, 0) -> 3858.1883 | F4: =IF(G4>0, E4 * (B4 - Assumptions!D$2), 0) -> 99433.903 | G4: =IF(I3>0, I3, 0) -> 3923929.7 | H4: =MAX(0, G4 - D4) -> 3479922.6 | I4: =IF(G4>0, MAX(0, H4 * (1 + Assumptions!B$5)), 0) -> 3862714.1
A5: =A4+1 -> 2029 | B5: =B4*(1+Assumptions!B$5) -> 127.74077 | C5: =MAX(0, MIN(G5, Main!D5)) -> 458329.23 | D5: =MAX(0, MIN(G5, C5)) -> 458329.23 | E5: =IF(B5>0, D5/B5, 0) -> 3587.9636 | F5: =IF(G5>0, E5 * (B5 - Assumptions!D$2), 0) -> 137889.64 | G5: =IF(I4>0, I4, 0) -> 3862714.1 | H5: =MAX(0, G5 - D5) -> 3404384.8 | I5: =IF(G5>0, MAX(0, H5 * (1 + Assumptions!B$5)), 0) -> 3778867.2
A6: =A5+1 -> 2030 | B6: =B5*(1+Assumptions!B$5) -> 141.79225 | C6: =MAX(0, MIN(G6, Main!D6)) -> 472831.53 | D6: =MAX(0, MIN(G6, C6)) -> 472831.53 | E6: =IF(B6>0, D6/B6, 0) -> 3334.6781 | F6: =IF(G6>0, E6 * (B6 - Assumptions!D$2), 0) -> 175012.76 | G6: =IF(I5>0, I5, 0) -> 3778867.2 | H6: =MAX(0, G6 - D6) -> 3306035.6 | I6: =IF(G6>0, MAX(0, H6 * (1 + Assumptions!B$5)), 0) -> 3669699.6
A7: =A6+1 -> 2031 | B7: =B6*(1+Assumptions!B$5) -> 157.3894 | C7: =MAX(0, MIN(G7, Main!D7)) -> 487493.59 | D7: =MAX(0, MIN(G7, C7)) -> 487493.59 | E7: =IF(B7>0, D7/B7, 0) -> 3097.3724 | F7: =IF(G7>0, E7 * (B7 - Assumptions!D$2), 0) -> 210868.5 | G7: =IF(I6>0, I6, 0) -> 3669699.6 | H7: =MAX(0, G7 - D7) -> 3182206 | I7: =IF(G7>0, MAX(0, H7 * (1 + Assumptions!B$5)), 0) -> 3532248.6
A8: =A7+1 -> 2032 | B8: =B7*(1+Assumptions!B$5) -> 174.70224 | C8: =MAX(0, MIN(G8, Main!D8)) -> 502291.76 | D8: =MAX(0, MIN(G8, C8)) -> 502291.76 | E8: =IF(B8>0, D8/B8, 0) -> 2875.1307 | F8: =IF(G8>0, E8 * (B8 - Assumptions!D$2), 0) -> 245514.99 | G8: =IF(I7>0, I7, 0) -> 3532248.6 | H8: =MAX(0, G8 - D8) -> 3029956.9 | I8: =IF(G8>0, MAX(0, H8 * (1 + Assumptions!B$5)), 0) -> 3363252.1
A9: =A8+1 -> 2033 | B9: =B8*(1+Assumptions!B$5) -> 193.91948 | C9: =MAX(0, MIN(G9, Main!D9)) -> 517198.8 | D9: =MAX(0, MIN(G9, C9)) -> 517198.8 | E9: =IF(B9>0, D9/B9, 0) -> 2667.0801 | F9: =IF(G9>0, E9 * (B9 - Assumptions!D$2), 0) -> 279002.94 | G9: =IF(I8>0, I8, 0) -> 3363252.1 | H9: =MAX(0, G9 - D9) -> 2846053.3 | I9: =IF(G9>0, MAX(0, H9 * (1 + Assumptions!B$5)), 0) -> 3159119.2
A10: =A9+1 -> 2034 | B10: =B9*(1+Assumptions!B$5) -> 215.25063 | C10: =MAX(0, MIN(G10, Main!D10)) -> 532183.54 | D10: =MAX(0, MIN(G10, C10)) -> 532183.54 | E10: =IF(B10>0, D10/B10, 0) -> 2472.3902 | F10: =IF(G10>0, E10 * (B10 - Assumptions!D$2), 0) -> 311375.36 | G10: =IF(I9>0, I9, 0) -> 3159119.2 | H10: =MAX(0, G10 - D10) -> 2626935.7 | I10: =IF(G10>0, MAX(0, H10 * (1 + Assumptions!B$5)), 0) -> 2915898.6
A11: =A10+1 -> 2035 | B11: =B10*(1+Assumptions!B$5) -> 238.9282 | C11: =MAX(0, MIN(G11, Main!D11)) -> 547210.4 | D11: =MAX(0, MIN(G11, C11)) -> 547210.4 | E11: =IF(B11>0, D11/B11, 0) -> 2290.2714 | F11: =IF(G11>0, E11 * (B11 - Assumptions!D$2), 0) -> 342667.18 | G11: =IF(I10>0, I10, 0) -> 2915898.6 | H11: =MAX(0, G11 - D11) -> 2368688.2 | I11: =IF(G11>0, MAX(0, H11 * (1 + Assumptions!B$5)), 0) -> 2629243.9
A12: =A11+1 -> 2036 | B12: =B11*(1+Assumptions!B$5) -> 265.2103 | C12: =MAX(0, MIN(G12, Main!D12)) -> 562238.94 | D12: =MAX(0, MIN(G12, C12)) -> 562238.94 | E12: =IF(B12>0, D12/B12, 0) -> 2119.974 | F12: =IF(G12>0, E12 * (B12 - Assumptions!D$2), 0) -> 372904.91 | G12: =IF(I11>0, I11, 0) -> 2629243.9 | H12: =MAX(0, G12 - D12) -> 2067004.9 | I12: =IF(G12>0, MAX(0, H12 * (1 + Assumptions!B$5)), 0) -> 2294375.5
A13: =A12+1 -> 2037 | B13: =B12*(1+Assumptions!B$5) -> 294.38343 | C13: =MAX(0, MIN(G13, Main!D13)) -> 577223.31 | D13: =MAX(0, MIN(G13, C13)) -> 577223.31 | E13: =IF(B13>0, D13/B13, 0) -> 1960.7874 | F13: =IF(G13>0, E13 * (B13 - Assumptions!D$2), 0) -> 402106.18 | G13: =IF(I12>0, I12, 0) -> 2294375.5 | H13: =MAX(0, G13 - D13) -> 1717152.2 | I13: =IF(G13>0, MAX(0, H13 * (1 + Assumptions!B$5)), 0) -> 1906038.9
A14: =A13+1 -> 2038 | B14: =B13*(1+Assumptions!B$5) -> 326.76561 | C14: =MAX(0, MIN(G14, Main!D14)) -> 592111.72 | D14: =MAX(0, MIN(G14, C14)) -> 592111.72 | E14: =IF(B14>0, D14/B14, 0) -> 1812.0381 | F14: =IF(G14>0, E14 * (B14 - Assumptions!D$2), 0) -> 430279.33 | G14: =IF(I13>0, I13, 0) -> 1906038.9 | H14: =MAX(0, G14 - D14) -> 1313927.2 | I14: =IF(G14>0, MAX(0, H14 * (1 + Assumptions!B$5)), 0) -> 1458459.2
... A31: =A30+1 -> 2055 | B31: =B30*(1+Assumptions!B$5) -> 1926.3135 | C31: =MAX(0, MIN(G31, Main!D31)) -> 0 | D31: =MAX(0, MIN(G31, C31)) -> 0 | E31: =IF(B31>0, D31/B31, 0) -> 0 | F31: =IF(G31>0, E31 * (B31 - Assumptions!D$2), 0) -> 0 | G31: =IF(I30>0, I30, 0) -> 0 | H31: =MAX(0, G31 - D31) -> 0 | I31: =IF(G31>0, MAX(0, H31 * (1 + Assumptions!B$5)), 0) -> 0
D33: =SUM(D2:D31) -> 7710771.9 | E33: =SUM(E2:E31) -> 38243.238 | F33: =SUM(F2:F31) -> 4608799.6
F35: =D33-F33 -> 3101972.3
